Workbook

Sheet Read Me
A1: SOC 2 Type II – Control Matrix & Evidence Tracker
A2: Scope: Security (Common Criteria CC1–CC9), AICPA 2017 Trust Services Criteria with Revised Points of Focus (2022). Tailored for GitHub Enterprise Cloud, GitHub Actions and ServiceNow; other subsystems vendor-neutral pending the Info Request.
A4: Organization | B4: [Company Name]
A5: System in scope | B5: [System / Product Name]
A6: Observation period | B6: [Start date] – [End date] (typically 3–12 months)
A7: Document owner | B7: [Compliance Manager]
A8: Version / date | B8: v1.1 – [Date] (GitHub / GitHub Actions / ServiceNow tailoring)
A10: HOW TO USE
A11: Yellow cells | B11: Fill-in fields. Replace placeholders and complete Named Owner, Tool Implemented, Status, Last Tested and PBC status columns.
A12: Blue italic text | B12: Example values showing expected format – overwrite with your own.
A13: Readiness Dashboard | B13: Calculated from Implementation Status in the Control Matrix. Do not edit – formulas.
A14: Control Matrix | B14: 69 controls mapped to all 33 Common Criteria. Each row lists subsystems, owner role, frequency, evidence, automation approach and Type II test procedure.
A15: TSC Coverage | B15: One row per Common Criterion with count of mapped controls (formula) and readiness status. Any 'GAP' must be resolved before fieldwork.
A16: Integration Inventory | B16: In-scope subsystems, how each integrates with the IdP, log pipeline and other subsystems, and what evidence it produces.
A17: Evidence Automation | B17: Scheduled collector jobs that pull evidence via API into the immutable evidence store.
A18: PBC Evidence List | B18: 'Provided By Client' request list – what the auditor will ask for, per control. Track status here during fieldwork.
A19: Risk Register | B19: Seed risk register with inherent/residual scoring (Likelihood × Impact, 1–5 scale). Adjust to your environment.
A20: Compliance Calendar | B20: Recurring control activities across the 12 months of the observation period (M1 = first month).
A21: GitHub-ServiceNow Config | B21: Required configuration settings for GitHub Enterprise Cloud, GitHub Actions and ServiceNow, how to verify each (API/UI), and the control it supports. Track status in the yellow columns.
A22: Info Request | B22: Questions to answer for the remaining subsystems (and open decisions on GitHub/ServiceNow) so the package can be fully tailored.
... A25: Important | B25: This is a template. Control descriptions must reflect what you actually do; auditors test the controls as written. Remove or edit any control you do not operate, and re-check TSC Coverage afterwards.

Sheet Info Request
A1: # | B1: Area | C1: Subsystem | D1: Question | E1: Why It's Needed | F1: Controls Affected | G1: Answer | H1: Answered By / Date
A2: 1 | B2: Organization | C2: General | D2: Legal entity name, system/product name, and a one-paragraph description of the service | E2: System description (SYS-001 §1) | F2: GOV-08
A3: 2 | B3: Organization | C3: General | D3: Headcount (employees/contractors) and org chart for Security, Platform/SRE, IT, Engineering | E3: People section; RACI; owners | F3: GOV-03
A4: 3 | B4: Organization | C4: General | D4: Target observation period (start date, length) and audit firm (if selected) | E4: Calendar, sampling, readiness plan | F4: GOV-05
A5: 4 | B5: Organization | C5: General | D5: Customer data types processed (PII? payment? health?) and hosting regions | E5: Classification, encryption, CUECs | F5: INF-05, POL-09
A6: 5 | B6: Organization | C6: General | D6: Existing policies, prior audits/pen tests, or known gaps | E6: Avoid duplication; gap analysis | F6: GOV-01
A7: 6 | B7: GitHub | C7: SCM | D7: Q1: GitHub Enterprise Cloud with EMU, Enterprise Cloud with SAML (personal accounts), or Enterprise Server (version)? | E7: Identity, SCIM, audit-log design | F7: IAM-01, IAM-03, MON-01
A8: 7 | B8: GitHub | C8: SCM | D8: Q2: Are GitHub Secret Protection and Code Security licensed for all in-scope repos? | E8: Else third-party SAST/SCA/secret scanners | F8: CHG-04, INF-06
A9: 8 | B9: GitHub | C9: SCM | D9: Q6: Number of GitHub organizations and in-scope repositories (list or estimate) | E9: Ruleset scope; populations | F9: CHG-01, GOV-08
A10: 9 | B10: GitHub | C10: SCM | D10: Is there a monorepo, and are any production repos public? | E10: Ruleset and fork settings | F10: CHG-01, INF-11
A11: 10 | B11: GitHub Actions | C11: CI | D11: Q3: GitHub-hosted, self-hosted, or both runners? If self-hosted: platform (ARC/Kubernetes, VMs) and network location | E11: Runner hardening; prod network path | F11: CHG-11
A12: 11 | B12: GitHub Actions | C12: CI | D12: Q7: Where are artifacts/images stored (GHCR/GitHub Packages or cloud registry)? | E12: Attestation and admission design | F12: CHG-07
A13: 12 | B13: GitHub Actions | C13: CI | D13: Q8: Any production deploys outside GitHub Actions today (manual, scripts, other CD tools e.g. Argo CD)? | E13: Must be brought under the gate before period start | F13: CHG-05
... A35: 34 | B35: Vendors | C35: VEN | D35: List of vendors with access to customer data or production (sub-service organizations) | E35: Carve-outs, CSOCs, VEN controls | F35: VEN-01, VEN-02
D37: Answered | E37: =COUNTA(G2:G35)&" of "&COUNTA(D2:D35) -> 0 of 34

Sheet Readiness Dashboard
A1: Readiness Dashboard
A2: All values are formulas driven by 'Control Matrix' column R (Implementation Status).
A4: Domain | B4: Controls | C4: Implemented | D4: Partial | E4: Not impl. | F4: N/A | G4: % Implemented
A5: Governance | B5: =COUNTIF('Control Matrix'!$B$2:$B$70,A5) -> 8 | C5: =COUNTIFS('Control Matrix'!$B$2:$B$70,A5,'Control Matrix'!$R$2:$R$70,"Implemented") -> 1 | D5: =COUNTIFS('Control Matrix'!$B$2:$B$70,A5,'Control Matrix'!$R$2:$R$70,"Partially implemented") -> 0 | E5: =COUNTIFS('Control Matrix'!$B$2:$B$70,A5,'Control Matrix'!$R$2:$R$70,"Not implemented") -> 0 | F5: =COUNTIFS('Control Matrix'!$B$2:$B$70,A5,'Control Matrix'!$R$2:$R$70,"Not applicable") -> 0 | G5: =IF((B5-F5)=0,0,C5/(B5-F5)) -> 0.125
A6: Human Resources | B6: =COUNTIF('Control Matrix'!$B$2:$B$70,A6) -> 5 | C6: =COUNTIFS('Control Matrix'!$B$2:$B$70,A6,'Control Matrix'!$R$2:$R$70,"Implemented") -> 0 | D6: =COUNTIFS('Control Matrix'!$B$2:$B$70,A6,'Control Matrix'!$R$2:$R$70,"Partially implemented") -> 0 | E6: =COUNTIFS('Control Matrix'!$B$2:$B$70,A6,'Control Matrix'!$R$2:$R$70,"Not implemented") -> 0 | F6: =COUNTIFS('Control Matrix'!$B$2:$B$70,A6,'Control Matrix'!$R$2:$R$70,"Not applicable") -> 0 | G6: =IF((B6-F6)=0,0,C6/(B6-F6)) -> 0
A7: Risk Management | B7: =COUNTIF('Control Matrix'!$B$2:$B$70,A7) -> 4 | C7: =COUNTIFS('Control Matrix'!$B$2:$B$70,A7,'Control Matrix'!$R$2:$R$70,"Implemented") -> 0 | D7: =COUNTIFS('Control Matrix'!$B$2:$B$70,A7,'Control Matrix'!$R$2:$R$70,"Partially implemented") -> 0 | E7: =COUNTIFS('Control Matrix'!$B$2:$B$70,A7,'Control Matrix'!$R$2:$R$70,"Not implemented") -> 0 | F7: =COUNTIFS('Control Matrix'!$B$2:$B$70,A7,'Control Matrix'!$R$2:$R$70,"Not applicable") -> 0 | G7: =IF((B7-F7)=0,0,C7/(B7-F7)) -> 0
A8: Vendor Management | B8: =COUNTIF('Control Matrix'!$B$2:$B$70,A8) -> 3 | C8: =COUNTIFS('Control Matrix'!$B$2:$B$70,A8,'Control Matrix'!$R$2:$R$70,"Implemented") -> 0 | D8: =COUNTIFS('Control Matrix'!$B$2:$B$70,A8,'Control Matrix'!$R$2:$R$70,"Partially implemented") -> 0 | E8: =COUNTIFS('Control Matrix'!$B$2:$B$70,A8,'Control Matrix'!$R$2:$R$70,"Not implemented") -> 0 | F8: =COUNTIFS('Control Matrix'!$B$2:$B$70,A8,'Control Matrix'!$R$2:$R$70,"Not applicable") -> 0 | G8: =IF((B8-F8)=0,0,C8/(B8-F8)) -> 0
A9: Identity & Access | B9: =COUNTIF('Control Matrix'!$B$2:$B$70,A9) -> 9 | C9: =COUNTIFS('Control Matrix'!$B$2:$B$70,A9,'Control Matrix'!$R$2:$R$70,"Implemented") -> 0 | D9: =COUNTIFS('Control Matrix'!$B$2:$B$70,A9,'Control Matrix'!$R$2:$R$70,"Partially implemented") -> 0 | E9: =COUNTIFS('Control Matrix'!$B$2:$B$70,A9,'Control Matrix'!$R$2:$R$70,"Not implemented") -> 0 | F9: =COUNTIFS('Control Matrix'!$B$2:$B$70,A9,'Control Matrix'!$R$2:$R$70,"Not applicable") -> 0 | G9: =IF((B9-F9)=0,0,C9/(B9-F9)) -> 0
A10: Change Management | B10: =COUNTIF('Control Matrix'!$B$2:$B$70,A10) -> 12 | C10: =COUNTIFS('Control Matrix'!$B$2:$B$70,A10,'Control Matrix'!$R$2:$R$70,"Implemented") -> 0 | D10: =COUNTIFS('Control Matrix'!$B$2:$B$70,A10,'Control Matrix'!$R$2:$R$70,"Partially implemented") -> 0 | E10: =COUNTIFS('Control Matrix'!$B$2:$B$70,A10,'Control Matrix'!$R$2:$R$70,"Not implemented") -> 0 | F10: =COUNTIFS('Control Matrix'!$B$2:$B$70,A10,'Control Matrix'!$R$2:$R$70,"Not applicable") -> 0 | G10: =IF((B10-F10)=0,0,C10/(B10-F10)) -> 0
A11: Infrastructure | B11: =COUNTIF('Control Matrix'!$B$2:$B$70,A11) -> 11 | C11: =COUNTIFS('Control Matrix'!$B$2:$B$70,A11,'Control Matrix'!$R$2:$R$70,"Implemented") -> 0 | D11: =COUNTIFS('Control Matrix'!$B$2:$B$70,A11,'Control Matrix'!$R$2:$R$70,"Partially implemented") -> 0 | E11: =COUNTIFS('Control Matrix'!$B$2:$B$70,A11,'Control Matrix'!$R$2:$R$70,"Not implemented") -> 0 | F11: =COUNTIFS('Control Matrix'!$B$2:$B$70,A11,'Control Matrix'!$R$2:$R$70,"Not applicable") -> 0 | G11: =IF((B11-F11)=0,0,C11/(B11-F11)) -> 0
A12: Vulnerability Management | B12: =COUNTIF('Control Matrix'!$B$2:$B$70,A12) -> 3 | C12: =COUNTIFS('Control Matrix'!$B$2:$B$70,A12,'Control Matrix'!$R$2:$R$70,"Implemented") -> 0 | D12: =COUNTIFS('Control Matrix'!$B$2:$B$70,A12,'Control Matrix'!$R$2:$R$70,"Partially implemented") -> 0 | E12: =COUNTIFS('Control Matrix'!$B$2:$B$70,A12,'Control Matrix'!$R$2:$R$70,"Not implemented") -> 0 | F12: =COUNTIFS('Control Matrix'!$B$2:$B$70,A12,'Control Matrix'!$R$2:$R$70,"Not applicable") -> 0 | G12: =IF((B12-F12)=0,0,C12/(B12-F12)) -> 0
A13: Logging & Monitoring | B13: =COUNTIF('Control Matrix'!$B$2:$B$70,A13) -> 6 | C13: =COUNTIFS('Control Matrix'!$B$2:$B$70,A13,'Control Matrix'!$R$2:$R$70,"Implemented") -> 0 | D13: =COUNTIFS('Control Matrix'!$B$2:$B$70,A13,'Control Matrix'!$R$2:$R$70,"Partially implemented") -> 0 | E13: =COUNTIFS('Control Matrix'!$B$2:$B$70,A13,'Control Matrix'!$R$2:$R$70,"Not implemented") -> 0 | F13: =COUNTIFS('Control Matrix'!$B$2:$B$70,A13,'Control Matrix'!$R$2:$R$70,"Not applicable") -> 0 | G13: =IF((B13-F13)=0,0,C13/(B13-F13)) -> 0
A14: Incident Response | B14: =COUNTIF('Control Matrix'!$B$2:$B$70,A14) -> 4 | C14: =COUNTIFS('Control Matrix'!$B$2:$B$70,A14,'Control Matrix'!$R$2:$R$70,"Implemented") -> 0 | D14: =COUNTIFS('Control Matrix'!$B$2:$B$70,A14,'Control Matrix'!$R$2:$R$70,"Partially implemented") -> 0 | E14: =COUNTIFS('Control Matrix'!$B$2:$B$70,A14,'Control Matrix'!$R$2:$R$70,"Not implemented") -> 0 | F14: =COUNTIFS('Control Matrix'!$B$2:$B$70,A14,'Control Matrix'!$R$2:$R$70,"Not applicable") -> 0 | G14: =IF((B14-F14)=0,0,C14/(B14-F14)) -> 0
A15: Business Continuity | B15: =COUNTIF('Control Matrix'!$B$2:$B$70,A15) -> 4 | C15: =COUNTIFS('Control Matrix'!$B$2:$B$70,A15,'Control Matrix'!$R$2:$R$70,"Implemented") -> 0 | D15: =COUNTIFS('Control Matrix'!$B$2:$B$70,A15,'Control Matrix'!$R$2:$R$70,"Partially implemented") -> 0 | E15: =COUNTIFS('Control Matrix'!$B$2:$B$70,A15,'Control Matrix'!$R$2:$R$70,"Not implemented") -> 0 | F15: =COUNTIFS('Control Matrix'!$B$2:$B$70,A15,'Control Matrix'!$R$2:$R$70,"Not applicable") -> 0 | G15: =IF((B15-F15)=0,0,C15/(B15-F15)) -> 0
A16: TOTAL | B16: =SUM(B5:B15) -> 69 | C16: =SUM(C5:C15) -> 1 | D16: =SUM(D5:D15) -> 0 | E16: =SUM(E5:E15) -> 0 | F16: =SUM(F5:F15) -> 0 | G16: =IF((B16-F16)=0,0,C16/(B16-F16)) -> 0.014492754
A18: Criteria coverage
A19: Common Criteria in scope | B19: =COUNTA('TSC Coverage'!A2:A34) -> 33
A20: Criteria with design GAP | B20: =COUNTIF('TSC Coverage'!F2:F34,"GAP") -> 0
A21: Criteria fully ready | B21: =COUNTIF('TSC Coverage'!G2:G34,"Ready") -> 1
A22: PBC items received | B22: =COUNTIF('PBC Evidence List'!I:I,"Received")+COUNTIF('PBC Evidence List'!I:I,"Accepted") -> 0
A23: PBC items total | B23: =COUNTA('PBC Evidence List'!A:A)-1 -> 135
A24: Residual risks rated Medium/High (score ≥ 8) | B24: =COUNTIF('Risk Register'!K2:K200,">=8") -> 2

Sheet Control Matrix
A1: Control ID | B1: Domain | C1: Control Title | D1: Control Description | E1: Subsystems | F1: Control Type | G1: Nature | H1: Frequency | I1: Owner (Role) | J1: TSC Mapping | K1: Evidence Required | L1: Evidence Automation | M1: Type II Test Procedure | N1: Sampling Basis | O1: Min. Sample | P1: Named Owner | Q1: Tool / System Implemented | R1: Implementation Status | S1: Last Tested | T1: Notes
A2: GOV-01 | B2: Governance | C2: Security policies approved and published | D2: Information security policies are reviewed at least annually, approved by executive management, version-controlled, and published to all personnel. | E2: GRC | F2: Preventive | G2: Manual | H2: Annual | I2: CISO / Security Lead | J2: CC1.1, CC2.2, CC5.3 | K2: Policy set with version history and approval record; publication location screenshot | L2: Policies stored as code in a policy repo; approval via PR review is captured automatically | M2: 1) Inquire of CISO / Security Lead. 2) Obtain the complete population of occurrences for the period and verify completeness (system-generated list). 3) Select a sample per the Sampling Guide. 4) Inspect evidence (Policy set with version history and approval record) for performance, timeliness, reviewer independence and follow-up of exceptions. | N2: Annual | O2: =IFERROR(INDEX('Sampling Guide'!$B$2:$B$20,MATCH(N2,'Sampling Guide'!$A$2:$A$20,0)),"TBD") -> 1 | P2: Jane Doe | Q2: e.g., GitHub policy repo + ServiceNow approval | R2: Implemented | S2: 2026-01-15 | T2: Example row – overwrite
A3: GOV-02 | B3: Governance | C3: Board / oversight committee security review | D3: The Board (or an oversight committee independent of management) receives a security and compliance update at least annually, including risk assessment results and control deficiencies. | E3: GRC | F3: Detective | G3: Manual | H3: Annual | I3: CEO | J3: CC1.2, CC4.2 | K3: Board / committee meeting minutes and presentation deck | L3: Manual upload to evidence store | M3: 1) Inquire of CEO. 2) Obtain the complete population of occurrences for the period and verify completeness (system-generated list). 3) Select a sample per the Sampling Guide. 4) Inspect evidence (Board / committee meeting minutes and presentation deck) for performance, timeliness, reviewer independence and follow-up of exceptions. | N3: Annual | O3: =IFERROR(INDEX('Sampling Guide'!$B$2:$B$20,MATCH(N3,'Sampling Guide'!$A$2:$A$20,0)),"TBD") -> 1
A4: GOV-03 | B4: Governance | C4: Organization chart and security roles defined | D4: An organization chart and a RACI of security and compliance responsibilities are maintained and reviewed annually. | E4: HRIS, GRC | F4: Preventive | G4: IT-dependent manual | H4: Annual | I4: Head of People | J4: CC1.3 | K4: Org chart export; RACI document with review date | L4: Org chart exported from HRIS by scheduled job | M4: 1) Inquire of Head of People. 2) Obtain the complete population of occurrences for the period and verify completeness (system-generated list). 3) Select a sample per the Sampling Guide. 4) Inspect evidence (Org chart export) for performance, timeliness, reviewer independence and follow-up of exceptions. | N4: Annual | O4: =IFERROR(INDEX('Sampling Guide'!$B$2:$B$20,MATCH(N4,'Sampling Guide'!$A$2:$A$20,0)),"TBD") -> 1
A5: GOV-04 | B5: Governance | C5: Security and compliance steering meeting | D5: A security steering group meets at least quarterly to review metrics, open risks, audit status and control failures; actions are tracked to closure. | E5: ITSM, GRC | F5: Detective | G5: Manual | H5: Quarterly | I5: CISO / Security Lead | J5: CC1.3, CC2.1, CC4.1, CC4.2 | K5: Meeting agendas, minutes and action tracker | L5: Action items tracked as tickets with label 'sec-steering' | M5: 1) Inquire of CISO / Security Lead. 2) Obtain the complete population of occurrences for the period and verify completeness (system-generated list). 3) Select a sample per the Sampling Guide. 4) Inspect evidence (Meeting agendas, minutes and action tracker) for performance, timeliness, reviewer independence and follow-up of exceptions. | N5: Quarterly | O5: =IFERROR(INDEX('Sampling Guide'!$B$2:$B$20,MATCH(N5,'Sampling Guide'!$A$2:$A$20,0)),"TBD") -> 2 | Q5: Action items tracked as ServiceNow tasks
A6: GOV-05 | B6: Governance | C6: Internal control self-assessment | D6: Control owners attest quarterly that their controls operated; the compliance function performs an annual internal assessment and tracks deficiencies to remediation. | E6: GRC, ITSM | F6: Detective | G6: IT-dependent manual | H6: Quarterly | I6: Compliance Manager | J6: CC4.1, CC4.2, CC5.1 | K6: Quarterly attestations; internal assessment report; deficiency tickets | L6: Automated control-health dashboard fed by evidence collectors | M6: 1) Inquire of Compliance Manager. 2) Obtain the complete population of occurrences for the period and verify completeness (system-generated list). 3) Select a sample per the Sampling Guide. 4) Inspect evidence (Quarterly attestations) for performance, timeliness, reviewer independence and follow-up of exceptions. | N6: Quarterly | O6: =IFERROR(INDEX('Sampling Guide'!$B$2:$B$20,MATCH(N6,'Sampling Guide'!$A$2:$A$20,0)),"TBD") -> 2
A7: GOV-06 | B7: Governance | C7: External communication of commitments | D7: Security commitments, system changes affecting customers, and incident notifications are communicated through contracts, the trust/status page and customer notices. | E7: GRC | F7: Preventive | G7: Manual | H7: Ongoing | I7: Legal / Compliance | J7: CC2.3 | K7: MSA/DPA templates; status page history; customer notices | L7: Status page history export | M7: 1) Inquire of Legal / Compliance. 2) Obtain the complete population of occurrences for the period and verify completeness (system-generated list). 3) Select a sample per the Sampling Guide. 4) Inspect evidence (MSA/DPA templates) for performance, timeliness, reviewer independence and follow-up of exceptions. | N7: Per event / multiple times per day | O7: =IFERROR(INDEX('Sampling Guide'!$B$2:$B$20,MATCH(N7,'Sampling Guide'!$A$2:$A$20,0)),"TBD") -> 25
A8: GOV-07 | B8: Governance | C8: Whistleblower / reporting channel | D8: An anonymous channel exists for personnel and external parties to report security concerns, fraud or ethics violations; reports are triaged and tracked. | E8: ITSM | F8: Detective | G8: Manual | H8: Ongoing | I8: Legal / Compliance | J8: CC1.1, CC2.2, CC2.3 | K8: Channel description in handbook; report log (redacted) | L8: n/a | M8: 1) Inquire of Legal / Compliance. 2) Obtain the complete population of occurrences for the period and verify completeness (system-generated list). 3) Select a sample per the Sampling Guide. 4) Inspect evidence (Channel description in handbook) for performance, timeliness, reviewer independence and follow-up of exceptions. | N8: Per event / multiple times per day | O8: =IFERROR(INDEX('Sampling Guide'!$B$2:$B$20,MATCH(N8,'Sampling Guide'!$A$2:$A$20,0)),"TBD") -> 25
A9: GOV-08 | B9: Governance | C9: System description and boundaries maintained | D9: The in-scope system description, data-flow diagrams and subsystem inventory are reviewed and updated at least annually and upon significant change. | E9: GRC, CLD | F9: Preventive | G9: IT-dependent manual | H9: Annual | I9: Compliance Manager | J9: CC2.1, CC3.4 | K9: Dated system description; architecture diagrams; integration inventory | L9: Cloud asset inventory export attached to review | M9: 1) Inquire of Compliance Manager. 2) Obtain the complete population of occurrences for the period and verify completeness (system-generated list). 3) Select a sample per the Sampling Guide. 4) Inspect evidence (Dated system description) for performance, timeliness, reviewer independence and follow-up of exceptions. | N9: Annual | O9: =IFERROR(INDEX('Sampling Guide'!$B$2:$B$20,MATCH(N9,'Sampling Guide'!$A$2:$A$20,0)),"TBD") -> 1 | Q9: In-scope repo list = GitHub custom property soc2_scope=true
A10: HR-01 | B10: Human Resources | C10: Background checks | D10: Background checks are completed for new hires prior to granting access to production or customer data, where legally permitted. | E10: HRIS | F10: Preventive | G10: IT-dependent manual | H10: Per event | I10: Head of People | J10: CC1.4 | K10: Background check completion records for sampled hires | L10: HRIS report of hires with check status | M10: 1) Inquire of Head of People. 2) Obtain the complete population of occurrences for the period and verify completeness (system-generated list). 3) Select a sample per the Sampling Guide. 4) Inspect evidence (Background check completion records for sampled hires) for performance, timeliness, reviewer independence and follow-up of exceptions. | N10: Per event / multiple times per day | O10: =IFERROR(INDEX('Sampling Guide'!$B$2:$B$20,MATCH(N10,'Sampling Guide'!$A$2:$A$20,0)),"TBD") -> 25
A11: HR-02 | B11: Human Resources | C11: Code of conduct and policy acknowledgment | D11: Personnel acknowledge the code of conduct, acceptable use and security policies at hire and annually. | E11: HRIS, GRC | F11: Preventive | G11: IT-dependent manual | H11: Per event / Annual | I11: Head of People | J11: CC1.1, CC1.5, CC2.2 | K11: Signed acknowledgments for sampled personnel | L11: HRIS/LMS acknowledgment export | M11: 1) Inquire of Head of People. 2) Obtain the complete population of occurrences for the period and verify completeness (system-generated list). 3) Select a sample per the Sampling Guide. 4) Inspect evidence (Signed acknowledgments for sampled personnel) for performance, timeliness, reviewer independence and follow-up of exceptions. | N11: Per event / multiple times per day | O11: =IFERROR(INDEX('Sampling Guide'!$B$2:$B$20,MATCH(N11,'Sampling Guide'!$A$2:$A$20,0)),"TBD") -> 25
A12: HR-03 | B12: Human Resources | C12: Security awareness training | D12: Personnel complete security awareness training within 30 days of hire and annually; engineers complete secure-coding training annually. | E12: HRIS, GRC | F12: Preventive | G12: IT-dependent manual | H12: Per event / Annual | I12: CISO / Security Lead | J12: CC1.4, CC2.2 | K12: Training completion report; training content | L12: LMS completion export on schedule | M12: 1) Inquire of CISO / Security Lead. 2) Obtain the complete population of occurrences for the period and verify completeness (system-generated list). 3) Select a sample per the Sampling Guide. 4) Inspect evidence (Training completion report) for performance, timeliness, reviewer independence and follow-up of exceptions. | N12: Per event / multiple times per day | O12: =IFERROR(INDEX('Sampling Guide'!$B$2:$B$20,MATCH(N12,'Sampling Guide'!$A$2:$A$20,0)),"TBD") -> 25
A13: HR-04 | B13: Human Resources | C13: Job descriptions and performance reviews | D13: Roles have documented job descriptions including security responsibilities; performance evaluations occur at least annually. | E13: HRIS | F13: Preventive | G13: Manual | H13: Annual | I13: Head of People | J13: CC1.3, CC1.4, CC1.5 | K13: Job descriptions; completed performance review evidence (sampled) | L13: HRIS report | M13: 1) Inquire of Head of People. 2) Obtain the complete population of occurrences for the period and verify completeness (system-generated list). 3) Select a sample per the Sampling Guide. 4) Inspect evidence (Job descriptions) for performance, timeliness, reviewer independence and follow-up of exceptions. | N13: Annual | O13: =IFERROR(INDEX('Sampling Guide'!$B$2:$B$20,MATCH(N13,'Sampling Guide'!$A$2:$A$20,0)),"TBD") -> 1
A14: HR-05 | B14: Human Resources | C14: Disciplinary process | D14: A documented sanctions process applies to personnel who violate security policies. | E14: HRIS | F14: Corrective | G14: Manual | H14: Per event | I14: Head of People | J14: CC1.5 | K14: Handbook sanctions section; case log if any | L14: n/a | M14: 1) Inquire of Head of People. 2) Obtain the complete population of occurrences for the period and verify completeness (system-generated list). 3) Select a sample per the Sampling Guide. 4) Inspect evidence (Handbook sanctions section) for performance, timeliness, reviewer independence and follow-up of exceptions. | N14: Per event / multiple times per day | O14: =IFERROR(INDEX('Sampling Guide'!$B$2:$B$20,MATCH(N14,'Sampling Guide'!$A$2:$A$20,0)),"TBD") -> 25
A15: RSK-01 | B15: Risk Management | C15: Annual risk assessment | D15: A formal risk assessment, including fraud risk and technology/threat changes, is performed at least annually; risks are scored and assigned owners and treatment plans. | E15: GRC | F15: Detective | G15: Manual | H15: Annual | I15: CISO / Security Lead | J15: CC3.1, CC3.2, CC3.3, CC3.4, CC5.1 | K15: Risk assessment report; risk register with scores and treatment | L15: Risk register maintained in GRC tool / workbook | M15: 1) Inquire of CISO / Security Lead. 2) Obtain the complete population of occurrences for the period and verify completeness (system-generated list). 3) Select a sample per the Sampling Guide. 4) Inspect evidence (Risk assessment report) for performance, timeliness, reviewer independence and follow-up of exceptions. | N15: Annual | O15: =IFERROR(INDEX('Sampling Guide'!$B$2:$B$20,MATCH(N15,'Sampling Guide'!$A$2:$A$20,0)),"TBD") -> 1
A16: RSK-02 | B16: Risk Management | C16: Security objectives defined | D16: Security objectives aligned with service commitments and system requirements are documented and reviewed annually. | E16: GRC | F16: Preventive | G16: Manual | H16: Annual | I16: CISO / Security Lead | J16: CC3.1 | K16: Documented objectives with approval | L16: n/a | M16: 1) Inquire of CISO / Security Lead. 2) Obtain the complete population of occurrences for the period and verify completeness (system-generated list). 3) Select a sample per the Sampling Guide. 4) Inspect evidence (Documented objectives with approval) for performance, timeliness, reviewer independence and follow-up of exceptions. | N16: Annual | O16: =IFERROR(INDEX('Sampling Guide'!$B$2:$B$20,MATCH(N16,'Sampling Guide'!$A$2:$A$20,0)),"TBD") -> 1
A17: RSK-03 | B17: Risk Management | C17: Change-driven risk review | D17: Significant changes (new subsystem, vendor, region, acquisition, architecture change) trigger a risk review before go-live. | E17: ITSM, GRC | F17: Preventive | G17: Manual | H17: Per event | I17: CISO / Security Lead | J17: CC3.4, CC9.1 | K17: Architecture/security review tickets for significant changes | L17: Ticket type 'security-review' required by intake workflow | M17: 1) Inquire of CISO / Security Lead. 2) Obtain the complete population of occurrences for the period and verify completeness (system-generated list). 3) Select a sample per the Sampling Guide. 4) Inspect evidence (Architecture/security review tickets for significant changes) for performance, timeliness, reviewer independence and follow-up of exceptions. | N17: Per event / multiple times per day | O17: =IFERROR(INDEX('Sampling Guide'!$B$2:$B$20,MATCH(N17,'Sampling Guide'!$A$2:$A$20,0)),"TBD") -> 25 | Q17: ServiceNow catalog item 'Security design review' for significant changes
A18: RSK-04 | B18: Risk Management | C18: Cyber insurance | D18: Cyber liability insurance is maintained and reviewed annually for adequacy. | E18: GRC | F18: Corrective | G18: Manual | H18: Annual | I18: CFO | J18: CC9.1 | K18: Insurance certificate / policy summary | L18: n/a | M18: 1) Inquire of CFO. 2) Obtain the complete population of occurrences for the period and verify completeness (system-generated list). 3) Select a sample per the Sampling Guide. 4) Inspect evidence (Insurance certificate / policy summary) for performance, timeliness, reviewer independence and follow-up of exceptions. | N18: Annual | O18: =IFERROR(INDEX('Sampling Guide'!$B$2:$B$20,MATCH(N18,'Sampling Guide'!$A$2:$A$20,0)),"TBD") -> 1
A19: VEN-01 | B19: Vendor Management | C19: Vendor inventory and risk tiering | D19: All vendors and sub-service organizations processing company or customer data are inventoried and risk-tiered. | E19: GRC | F19: Preventive | G19: Manual | H19: Ongoing / Annual review | I19: Compliance Manager | J19: CC9.2 | K19: Vendor inventory with tier and data classification | L19: Inventory seeded from SSO app catalog and AP spend report | M19: 1) Inquire of Compliance Manager. 2) Obtain the complete population of occurrences for the period and verify completeness (system-generated list). 3) Select a sample per the Sampling Guide. 4) Inspect evidence (Vendor inventory with tier and data classification) for performance, timeliness, reviewer independence and follow-up of exceptions. | N19: Per event / multiple times per day | O19: =IFERROR(INDEX('Sampling Guide'!$B$2:$B$20,MATCH(N19,'Sampling Guide'!$A$2:$A$20,0)),"TBD") -> 25
A20: VEN-02 | B20: Vendor Management | C20: Vendor security due diligence | D20: Before onboarding and annually for critical vendors, security posture is reviewed (SOC 2 report, questionnaire), including complementary user entity controls (CUECs). | E20: GRC | F20: Detective | G20: Manual | H20: Per event / Annual | I20: Compliance Manager | J20: CC9.2, CC2.3 | K20: Vendor SOC reports and review memos incl. CUEC mapping | L20: Reminder tickets auto-generated 30 days before review due | M20: 1) Inquire of Compliance Manager. 2) Obtain the complete population of occurrences for the period and verify completeness (system-generated list). 3) Select a sample per the Sampling Guide. 4) Inspect evidence (Vendor SOC reports and review memos incl. CUEC mapping) for performance, timeliness, reviewer independence and follow-up of exceptions. | N20: Per event / multiple times per day | O20: =IFERROR(INDEX('Sampling Guide'!$B$2:$B$20,MATCH(N20,'Sampling Guide'!$A$2:$A$20,0)),"TBD") -> 25 | Q20: ServiceNow task / VRM (if licensed) generated 30 days before review
A21: VEN-03 | B21: Vendor Management | C21: Vendor contracts include security terms | D21: Contracts with critical vendors include confidentiality, security, breach notification and right-to-audit terms. | E21: GRC | F21: Preventive | G21: Manual | H21: Per event | I21: Legal / Compliance | J21: CC9.2 | K21: Executed contracts/DPAs for sampled vendors | L21: n/a | M21: 1) Inquire of Legal / Compliance. 2) Obtain the complete population of occurrences for the period and verify completeness (system-generated list). 3) Select a sample per the Sampling Guide. 4) Inspect evidence (Executed contracts/DPAs for sampled vendors) for performance, timeliness, reviewer independence and follow-up of exceptions. | N21: Per event / multiple times per day | O21: =IFERROR(INDEX('Sampling Guide'!$B$2:$B$20,MATCH(N21,'Sampling Guide'!$A$2:$A$20,0)),"TBD") -> 25
A22: IAM-01 | B22: Identity & Access | C22: Centralized SSO with MFA | D22: Access to in-scope subsystems (SCM, CI/CD, cloud console/API, SIEM, ITSM, registry) is federated through the IdP with phishing-resistant MFA enforced; local accounts are disabled or break-glass only. | E22: IDP, SCM, CI, CLD, SIEM, ITSM, REG | F22: Preventive | G22: Automated | H22: Continuous | I22: IT / Identity Admin | J22: CC6.1, CC6.2 | K22: IdP authentication policy config; per-app SSO enforcement settings; list of local accounts | L22: Nightly collector exports IdP policies and app SSO settings via API | M22: 1) Inquire of IT / Identity Admin to understand the control. 2) Inspect the configuration in IDP, SCM, CI, CLD, SIEM, ITSM, REG at a point in time. 3) Inspect change/drift history to confirm the configuration was in effect throughout the period. 4) Where feasible, re-perform (attempt a prohibited action) and observe it is blocked or alerted. 5) Rely on ITGCs (CHG-01, IAM-04) over the configuration. | N22: Automated (continuous) | O22: =IFERROR(INDEX('Sampling Guide'!$B$2:$B$20,MATCH(N22,'Sampling Guide'!$A$2:$A$20,0)),"TBD") -> 1 | Q22: GitHub EMU / enterprise SAML SSO via [IdP]; ServiceNow SAML SSO via [IdP]; local logins disabled (break-glass only)
A23: IAM-02 | B23: Identity & Access | C23: HRIS-driven provisioning (joiner) | D23: New user identities are created in the IdP from the HRIS joiner event; application access is granted via role-based groups following an approved access request. | E23: HRIS, IDP, ITSM | F23: Preventive | G23: Automated | H23: Per event | I23: IT / Identity Admin | J23: CC6.2, CC6.3 | K23: Joiner events; access request tickets with approval for sampled hires | L23: SCIM/HRIS webhook logs; ITSM approval records | M23: 1) Inquire of IT / Identity Admin to understand the control. 2) Inspect the configuration in HRIS, IDP, ITSM at a point in time. 3) Inspect change/drift history to confirm the configuration was in effect throughout the period. 4) Where feasible, re-perform (attempt a prohibited action) and observe it is blocked or alerted. 5) Rely on ITGCs (CHG-01, IAM-04) over the configuration. | N23: Per event / multiple times per day | O23: =IFERROR(INDEX('Sampling Guide'!$B$2:$B$20,MATCH(N23,'Sampling Guide'!$A$2:$A$20,0)),"TBD") -> 25 | Q23: ServiceNow catalog item 'Access to in-scope system' (manager + system-owner approval) → IdP group → SCIM to GitHub / ServiceNow
A24: IAM-03 | B24: Identity & Access | C24: Timely deprovisioning (leaver) | D24: Terminated users are disabled in the IdP within 24 hours of termination (immediately for involuntary); downstream app access and tokens are revoked via SCIM. | E24: HRIS, IDP, SCM, CLD | F24: Preventive | G24: Automated | H24: Per event | I24: IT / Identity Admin | J24: CC6.2, CC6.3 | K24: HRIS termination list vs. IdP deactivation timestamps | L24: Daily reconciliation job flags leavers active >24h and opens ticket | M24: 1) Inquire of IT / Identity Admin to understand the control. 2) Inspect the configuration in HRIS, IDP, SCM, CLD at a point in time. 3) Inspect change/drift history to confirm the configuration was in effect throughout the period. 4) Where feasible, re-perform (attempt a prohibited action) and observe it is blocked or alerted. 5) Rely on ITGCs (CHG-01, IAM-04) over the configuration. | N24: Per event / multiple times per day | O24: =IFERROR(INDEX('Sampling Guide'!$B$2:$B$20,MATCH(N24,'Sampling Guide'!$A$2:$A$20,0)),"TBD") -> 25 | Q24: IdP deactivation → SCIM suspends GitHub (EMU) user; ServiceNow user active=false; leaver recon ticket in ServiceNow
A25: IAM-04 | B25: Identity & Access | C25: Quarterly user access reviews | D25: System owners review user and privileged access to in-scope subsystems quarterly; inappropriate access is removed and tracked to closure. | E25: IDP, SCM, CLD, CI, SIEM, ITSM | F25: Detective | G25: IT-dependent manual | H25: Quarterly | I25: System Owners | J25: CC6.2, CC6.3, CC4.1 | K25: Access review workbooks with reviewer sign-off; removal tickets | L25: Collector generates user lists per system; completeness via API row counts | M25: 1) Inquire of System Owners. 2) Obtain the complete population of occurrences for the period and verify completeness (system-generated list). 3) Select a sample per the Sampling Guide. 4) Inspect evidence (Access review workbooks with reviewer sign-off) for performance, timeliness, reviewer independence and follow-up of exceptions. | N25: Quarterly | O25: =IFERROR(INDEX('Sampling Guide'!$B$2:$B$20,MATCH(N25,'Sampling Guide'!$A$2:$A$20,0)),"TBD") -> 2 | Q25: Quarterly: GitHub org owners/members/teams/outside collaborators; ServiceNow sys_user_has_role (admin, security_admin, change_manager, CAB)
A26: IAM-05 | B26: Identity & Access | C26: Least privilege and role-based access | D26: Access is granted through predefined roles/groups; production write access is restricted to on-call/SRE roles; standing admin access is minimized. | E26: IDP, CLD, K8S | F26: Preventive | G26: Automated | H26: Continuous | I26: Engineering Manager | J26: CC6.1, CC6.3 | K26: Role definitions; IAM policy exports; group membership | L26: IaC-managed IAM; policy-as-code checks in CI | M26: 1) Inquire of Engineering Manager to understand the control. 2) Inspect the configuration in IDP, CLD, K8S at a point in time. 3) Inspect change/drift history to confirm the configuration was in effect throughout the period. 4) Where feasible, re-perform (attempt a prohibited action) and observe it is blocked or alerted. 5) Rely on ITGCs (CHG-01, IAM-04) over the configuration. | N26: Automated (continuous) | O26: =IFERROR(INDEX('Sampling Guide'!$B$2:$B$20,MATCH(N26,'Sampling Guide'!$A$2:$A$20,0)),"TBD") -> 1 | Q26: GitHub base permission = none; repo admin via teams; ServiceNow roles only via groups
A27: IAM-06 | B27: Identity & Access | C27: Just-in-time privileged access | D27: Privileged production access is time-bound, requested with justification, approved, and logged. | E27: IDP, CLD, ITSM, SIEM | F27: Preventive | G27: Automated | H27: Per event | I27: Engineering Manager | J27: CC6.1, CC6.3, CC7.2 | K27: JIT elevation logs with approvals and expiry | L27: Elevation events forwarded to SIEM | M27: 1) Inquire of Engineering Manager to understand the control. 2) Inspect the configuration in IDP, CLD, ITSM, SIEM at a point in time. 3) Inspect change/drift history to confirm the configuration was in effect throughout the period. 4) Where feasible, re-perform (attempt a prohibited action) and observe it is blocked or alerted. 5) Rely on ITGCs (CHG-01, IAM-04) over the configuration. | N27: Per event / multiple times per day | O27: =IFERROR(INDEX('Sampling Guide'!$B$2:$B$20,MATCH(N27,'Sampling Guide'!$A$2:$A$20,0)),"TBD") -> 25
A28: IAM-07 | B28: Identity & Access | C28: Service accounts and machine identities | D28: Non-human identities use workload identity federation (e.g., OIDC) or short-lived credentials; static keys are prohibited or rotated <=90 days and inventoried. | E28: CI, CLD, VAULT | F28: Preventive | G28: Automated | H28: Continuous | I28: Platform Engineering | J28: CC6.1, CC6.2 | K28: Service account inventory; key age report; OIDC trust config | L28: Weekly key-age scan; findings auto-ticketed | M28: 1) Inquire of Platform Engineering to understand the control. 2) Inspect the configuration in CI, CLD, VAULT at a point in time. 3) Inspect change/drift history to confirm the configuration was in effect throughout the period. 4) Where feasible, re-perform (attempt a prohibited action) and observe it is blocked or alerted. 5) Rely on ITGCs (CHG-01, IAM-04) over the configuration. | N28: Automated (continuous) | O28: =IFERROR(INDEX('Sampling Guide'!$B$2:$B$20,MATCH(N28,'Sampling Guide'!$A$2:$A$20,0)),"TBD") -> 1 | Q28: GitHub: classic PATs blocked, fine-grained PATs approved ≤90d, GitHub Apps approved; OIDC for cloud; ServiceNow integration users web-service-only
A29: IAM-08 | B29: Identity & Access | C29: Password and authentication standards | D29: Authentication settings (length, lockout, session timeout) conform to the Access Control Policy. | E29: IDP | F29: Preventive | G29: Automated | H29: Continuous | I29: IT / Identity Admin | J29: CC6.1 | K29: IdP policy configuration export | L29: Nightly config export with drift diff | M29: 1) Inquire of IT / Identity Admin to understand the control. 2) Inspect the configuration in IDP at a point in time. 3) Inspect change/drift history to confirm the configuration was in effect throughout the period. 4) Where feasible, re-perform (attempt a prohibited action) and observe it is blocked or alerted. 5) Rely on ITGCs (CHG-01, IAM-04) over the configuration. | N29: Automated (continuous) | O29: =IFERROR(INDEX('Sampling Guide'!$B$2:$B$20,MATCH(N29,'Sampling Guide'!$A$2:$A$20,0)),"TBD") -> 1
A30: IAM-09 | B30: Identity & Access | C30: Break-glass accounts | D30: Emergency accounts are vaulted, MFA-protected, alert on use, and use is reviewed. | E30: VAULT, CLD, SIEM | F30: Detective | G30: Automated | H30: Per event | I30: CISO / Security Lead | J30: CC6.1, CC7.2 | K30: Break-glass inventory; alert rule; usage review tickets | L30: SIEM rule fires on any break-glass login | M30: 1) Inquire of CISO / Security Lead to understand the control. 2) Inspect the configuration in VAULT, CLD, SIEM at a point in time. 3) Inspect change/drift history to confirm the configuration was in effect throughout the period. 4) Where feasible, re-perform (attempt a prohibited action) and observe it is blocked or alerted. 5) Rely on ITGCs (CHG-01, IAM-04) over the configuration. | N30: Per event / multiple times per day | O30: =IFERROR(INDEX('Sampling Guide'!$B$2:$B$20,MATCH(N30,'Sampling Guide'!$A$2:$A$20,0)),"TBD") -> 25 | Q30: ServiceNow local admin + GitHub enterprise owner break-glass vaulted; SIEM alert on use
A31: CHG-01 | B31: Change Management | C31: Branch protection on default branches | D31: Default/release branches require pull requests, at least one approval from a code owner other than the author, passing status checks, and prohibit force-push and deletion; admins cannot bypass. | E31: SCM | F31: Preventive | G31: Automated | H31: Continuous | I31: Engineering Manager | J31: CC8.1, CC5.2 | K31: Branch protection/ruleset configuration export for in-scope repos | L31: Nightly collector exports rulesets; drift alerts to Security | M31: 1) Inquire of Engineering Manager to understand the control. 2) Inspect the configuration in SCM at a point in time. 3) Inspect change/drift history to confirm the configuration was in effect throughout the period. 4) Where feasible, re-perform (attempt a prohibited action) and observe it is blocked or alerted. 5) Rely on ITGCs (CHG-01, IAM-04) over the configuration. | N31: Automated (continuous) | O31: =IFERROR(INDEX('Sampling Guide'!$B$2:$B$20,MATCH(N31,'Sampling Guide'!$A$2:$A$20,0)),"TBD") -> 1 | Q31: GitHub org ruleset 'soc2-default-branch-protection' on repos with custom property soc2_scope=true; bypass list empty; tag ruleset for releases
A32: CHG-02 | B32: Change Management | C32: Peer review of code changes | D32: All changes merged to production branches are peer reviewed and approved by someone other than the author. | E32: SCM | F32: Preventive | G32: Automated | H32: Per event | I32: Engineering Manager | J32: CC8.1 | K32: Population of merged PRs with reviewer != author for sampled changes | L32: Collector pulls merged PR list + reviews via SCM API | M32: 1) Inquire of Engineering Manager to understand the control. 2) Inspect the configuration in SCM at a point in time. 3) Inspect change/drift history to confirm the configuration was in effect throughout the period. 4) Where feasible, re-perform (attempt a prohibited action) and observe it is blocked or alerted. 5) Rely on ITGCs (CHG-01, IAM-04) over the configuration. | N32: Per event / multiple times per day | O32: =IFERROR(INDEX('Sampling Guide'!$B$2:$B$20,MATCH(N32,'Sampling Guide'!$A$2:$A$20,0)),"TBD") -> 25 | Q32: Ruleset: code-owner review, require_last_push_approval, dismiss stale reviews; Actions not allowed to approve PRs
A33: CHG-03 | B33: Change Management | C33: Automated testing in CI | D33: CI runs unit/integration tests on every PR; failing tests block merge. | E33: CI, SCM | F33: Preventive | G33: Automated | H33: Per event | I33: Engineering Manager | J33: CC8.1 | K33: Required status checks config; CI run logs for sampled PRs | L33: CI run metadata archived to evidence store | M33: 1) Inquire of Engineering Manager to understand the control. 2) Inspect the configuration in CI, SCM at a point in time. 3) Inspect change/drift history to confirm the configuration was in effect throughout the period. 4) Where feasible, re-perform (attempt a prohibited action) and observe it is blocked or alerted. 5) Rely on ITGCs (CHG-01, IAM-04) over the configuration. | N33: Per event / multiple times per day | O33: =IFERROR(INDEX('Sampling Guide'!$B$2:$B$20,MATCH(N33,'Sampling Guide'!$A$2:$A$20,0)),"TBD") -> 25 | Q33: Required status check 'ci / test' in GitHub Actions
A34: CHG-04 | B34: Change Management | C34: Security scanning in pipeline | D34: SAST, dependency (SCA), secret scanning and container image scanning run in CI; critical/high findings block release unless an approved exception exists. | E34: CI, SEC, REG | F34: Preventive | G34: Automated | H34: Per event | I34: AppSec Lead | J34: CC8.1, CC7.1, CC6.8 | K34: Scanner config; pipeline gate policy; findings and exception tickets | L34: Scanner results exported to SIEM/GRC | M34: 1) Inquire of AppSec Lead to understand the control. 2) Inspect the configuration in CI, SEC, REG at a point in time. 3) Inspect change/drift history to confirm the configuration was in effect throughout the period. 4) Where feasible, re-perform (attempt a prohibited action) and observe it is blocked or alerted. 5) Rely on ITGCs (CHG-01, IAM-04) over the configuration. | N34: Per event / multiple times per day | O34: =IFERROR(INDEX('Sampling Guide'!$B$2:$B$20,MATCH(N34,'Sampling Guide'!$A$2:$A$20,0)),"TBD") -> 25 | Q34: CodeQL (ruleset code_scanning rule, High+ blocks), dependency-review action, secret scanning push protection with delegated bypass
A35: CHG-05 | B35: Change Management | C35: Pipeline-only production deployment | D35: Production deployments occur only through the CI/CD pipeline using a deploy identity; humans have no standing direct write/deploy access to production. | E35: CI, CLD, K8S | F35: Preventive | G35: Automated | H35: Continuous | I35: Platform Engineering | J35: CC8.1, CC6.1, CC5.2 | K35: Deploy role trust policy; IAM exports; cloud audit logs showing deploys by pipeline identity | L35: Monthly query of cloud audit logs for non-pipeline prod changes | M35: 1) Inquire of Platform Engineering to understand the control. 2) Inspect the configuration in CI, CLD, K8S at a point in time. 3) Inspect change/drift history to confirm the configuration was in effect throughout the period. 4) Where feasible, re-perform (attempt a prohibited action) and observe it is blocked or alerted. 5) Rely on ITGCs (CHG-01, IAM-04) over the configuration. | N35: Automated (continuous) | O35: =IFERROR(INDEX('Sampling Guide'!$B$2:$B$20,MATCH(N35,'Sampling Guide'!$A$2:$A$20,0)),"TBD") -> 1 | Q35: Cloud role trusts GitHub OIDC sub '...:environment:production' only; production environment with ServiceNow deployment gate; admin bypass disabled
A36: CHG-06 | B36: Change Management | C36: Deployment traceability | D36: Every production deployment is traceable to a commit SHA, approved PR, pipeline run and (where required) change ticket. | E36: CI, SCM, ITSM, REG | F36: Detective | G36: Automated | H36: Per event | I36: Engineering Manager | J36: CC8.1, CC2.1 | K36: Deployment log linking SHA -> PR -> pipeline run -> artifact digest | L36: Pipeline emits deployment record to evidence store | M36: 1) Inquire of Engineering Manager to understand the control. 2) Inspect the configuration in CI, SCM, ITSM, REG at a point in time. 3) Inspect change/drift history to confirm the configuration was in effect throughout the period. 4) Where feasible, re-perform (attempt a prohibited action) and observe it is blocked or alerted. 5) Rely on ITGCs (CHG-01, IAM-04) over the configuration. | N36: Per event / multiple times per day | O36: =IFERROR(INDEX('Sampling Guide'!$B$2:$B$20,MATCH(N36,'Sampling Guide'!$A$2:$A$20,0)),"TBD") -> 25 | Q36: ServiceNow DevOps Change Velocity change per production deployment; quarterly GitHub deployments ↔ ServiceNow change reconciliation
A37: CHG-07 | B37: Change Management | C37: Signed, provenance-attested artifacts | D37: Build artifacts are produced by the CI system, signed, and carry build provenance; admission policy rejects unsigned images in production. | E37: CI, REG, K8S | F37: Preventive | G37: Automated | H37: Continuous | I37: Platform Engineering | J37: CC8.1, CC6.8 | K37: Signing config; admission policy; sample verification output | L37: Admission controller logs to SIEM | M37: 1) Inquire of Platform Engineering to understand the control. 2) Inspect the configuration in CI, REG, K8S at a point in time. 3) Inspect change/drift history to confirm the configuration was in effect throughout the period. 4) Where feasible, re-perform (attempt a prohibited action) and observe it is blocked or alerted. 5) Rely on ITGCs (CHG-01, IAM-04) over the configuration. | N37: Automated (continuous) | O37: =IFERROR(INDEX('Sampling Guide'!$B$2:$B$20,MATCH(N37,'Sampling Guide'!$A$2:$A$20,0)),"TBD") -> 1 | Q37: actions/attest-build-provenance; 'gh attestation verify' before deploy; cluster admission policy
A38: CHG-08 | B38: Change Management | C38: Environment segregation | D38: Development, staging and production are logically separated (separate accounts/projects/clusters); production data is not used in non-production without approval and masking. | E38: CLD, K8S, IAC | F38: Preventive | G38: Automated | H38: Continuous | I38: Platform Engineering | J38: CC8.1, CC6.1 | K38: Account/project structure diagram; network config; IAM boundaries | L38: IaC state export | M38: 1) Inquire of Platform Engineering to understand the control. 2) Inspect the configuration in CLD, K8S, IAC at a point in time. 3) Inspect change/drift history to confirm the configuration was in effect throughout the period. 4) Where feasible, re-perform (attempt a prohibited action) and observe it is blocked or alerted. 5) Rely on ITGCs (CHG-01, IAM-04) over the configuration. | N38: Automated (continuous) | O38: =IFERROR(INDEX('Sampling Guide'!$B$2:$B$20,MATCH(N38,'Sampling Guide'!$A$2:$A$20,0)),"TBD") -> 1
A39: CHG-09 | B39: Change Management | C39: Emergency change procedure | D39: Emergency changes follow an expedited path and receive retrospective review and approval within 2 business days. | E39: ITSM, SCM | F39: Corrective | G39: IT-dependent manual | H39: Per event | I39: Engineering Manager | J39: CC8.1 | K39: Emergency change tickets with retrospective approval | L39: Ticket type 'emergency-change' with SLA timer | M39: 1) Inquire of Engineering Manager. 2) Obtain the complete population of occurrences for the period and verify completeness (system-generated list). 3) Select a sample per the Sampling Guide. 4) Inspect evidence (Emergency change tickets with retrospective approval) for performance, timeliness, reviewer independence and follow-up of exceptions. | N39: Per event / multiple times per day | O39: =IFERROR(INDEX('Sampling Guide'!$B$2:$B$20,MATCH(N39,'Sampling Guide'!$A$2:$A$20,0)),"TBD") -> 25 | Q39: ServiceNow Emergency change model; retrospective approval task ≤2 BD; ruleset bypass only via settings-as-code break-glass
A40: CHG-10 | B40: Change Management | C40: Infrastructure changes via IaC | D40: Infrastructure changes are defined in IaC, peer reviewed, planned in CI (plan output attached), and applied by the pipeline. | E40: IAC, SCM, CI, CLD | F40: Preventive | G40: Automated | H40: Per event | I40: Platform Engineering | J40: CC8.1, CC7.1 | K40: IaC PRs with plan output and approval; apply logs | L40: Pipeline archives plan/apply logs | M40: 1) Inquire of Platform Engineering to understand the control. 2) Inspect the configuration in IAC, SCM, CI, CLD at a point in time. 3) Inspect change/drift history to confirm the configuration was in effect throughout the period. 4) Where feasible, re-perform (attempt a prohibited action) and observe it is blocked or alerted. 5) Rely on ITGCs (CHG-01, IAM-04) over the configuration. | N40: Per event / multiple times per day | O40: =IFERROR(INDEX('Sampling Guide'!$B$2:$B$20,MATCH(N40,'Sampling Guide'!$A$2:$A$20,0)),"TBD") -> 25 | Q40: IaC PRs in GitHub; plan posted by Actions; apply by Actions via OIDC
A41: CHG-11 | B41: Change Management | C41: Pipeline configuration protected | D41: CI/CD pipeline definitions, runners and secrets are protected: workflow file changes require code-owner review; third-party actions/plugins are pinned by digest; runners are ephemeral. | E41: CI, SCM, VAULT | F41: Preventive | G41: Automated | H41: Continuous | I41: Platform Engineering | J41: CC8.1, CC6.1, CC6.8 | K41: CODEOWNERS for pipeline paths; pinning policy check; runner config | L41: Policy check in CI flags unpinned dependencies | M41: 1) Inquire of Platform Engineering to understand the control. 2) Inspect the configuration in CI, SCM, VAULT at a point in time. 3) Inspect change/drift history to confirm the configuration was in effect throughout the period. 4) Where feasible, re-perform (attempt a prohibited action) and observe it is blocked or alerted. 5) Rely on ITGCs (CHG-01, IAM-04) over the configuration. | N41: Automated (continuous) | O41: =IFERROR(INDEX('Sampling Guide'!$B$2:$B$20,MATCH(N41,'Sampling Guide'!$A$2:$A$20,0)),"TBD") -> 1 | Q41: Actions policy: allowed-actions list + require full-length SHA pinning; default GITHUB_TOKEN read-only; CODEOWNERS on .github/; ephemeral runners
A42: CHG-12 | B42: Change Management | C42: Secure SDLC and design review | D42: Significant features undergo threat modeling/security design review before development; SDLC is documented. | E42: ITSM, SCM | F42: Preventive | G42: Manual | H42: Per event | I42: AppSec Lead | J42: CC8.1, CC3.4 | K42: Design review tickets/threat models for sampled features | L42: Label-driven workflow in ITSM | M42: 1) Inquire of AppSec Lead. 2) Obtain the complete population of occurrences for the period and verify completeness (system-generated list). 3) Select a sample per the Sampling Guide. 4) Inspect evidence (Design review tickets/threat models for sampled features) for performance, timeliness, reviewer independence and follow-up of exceptions. | N42: Per event / multiple times per day | O42: =IFERROR(INDEX('Sampling Guide'!$B$2:$B$20,MATCH(N42,'Sampling Guide'!$A$2:$A$20,0)),"TBD") -> 25 | Q42: ServiceNow catalog item 'Security design review'
A43: INF-01 | B43: Infrastructure | C43: Hardened baseline configurations | D43: Cloud accounts, clusters and images are built from hardened baselines (e.g., CIS benchmarks) defined in code. | E43: IAC, CLD, K8S | F43: Preventive | G43: Automated | H43: Continuous | I43: Platform Engineering | J43: CC7.1, CC5.2 | K43: Baseline definitions; image build pipeline; benchmark scan results | L43: CSPM benchmark results exported weekly | M43: 1) Inquire of Platform Engineering to understand the control. 2) Inspect the configuration in IAC, CLD, K8S at a point in time. 3) Inspect change/drift history to confirm the configuration was in effect throughout the period. 4) Where feasible, re-perform (attempt a prohibited action) and observe it is blocked or alerted. 5) Rely on ITGCs (CHG-01, IAM-04) over the configuration. | N43: Automated (continuous) | O43: =IFERROR(INDEX('Sampling Guide'!$B$2:$B$20,MATCH(N43,'Sampling Guide'!$A$2:$A$20,0)),"TBD") -> 1
A44: INF-02 | B44: Infrastructure | C44: Configuration drift detection (CSPM) | D44: Cloud posture management continuously evaluates resources against policy; high-risk misconfigurations generate tickets with SLA. | E44: CLD, SEC, ITSM | F44: Detective | G44: Automated | H44: Continuous | I44: Platform Engineering | J44: CC7.1, CC4.1 | K44: CSPM policy set; findings trend; remediation tickets | L44: CSPM -> ITSM integration auto-creates tickets | M44: 1) Inquire of Platform Engineering to understand the control. 2) Inspect the configuration in CLD, SEC, ITSM at a point in time. 3) Inspect change/drift history to confirm the configuration was in effect throughout the period. 4) Where feasible, re-perform (attempt a prohibited action) and observe it is blocked or alerted. 5) Rely on ITGCs (CHG-01, IAM-04) over the configuration. | N44: Automated (continuous) | O44: =IFERROR(INDEX('Sampling Guide'!$B$2:$B$20,MATCH(N44,'Sampling Guide'!$A$2:$A$20,0)),"TBD") -> 1
A45: INF-03 | B45: Infrastructure | C45: Network security controls | D45: Production networks restrict inbound traffic to required ports via security groups/firewalls/WAF; administrative access uses zero-trust proxy or bastion with SSO; no public admin ports. | E45: CLD, IAC, K8S | F45: Preventive | G45: Automated | H45: Continuous | I45: Platform Engineering | J45: CC6.6, CC6.1 | K45: Firewall/security-group rules; WAF config; admin access path config | L45: IaC export; CSPM rule for 0.0.0.0/0 on admin ports | M45: 1) Inquire of Platform Engineering to understand the control. 2) Inspect the configuration in CLD, IAC, K8S at a point in time. 3) Inspect change/drift history to confirm the configuration was in effect throughout the period. 4) Where feasible, re-perform (attempt a prohibited action) and observe it is blocked or alerted. 5) Rely on ITGCs (CHG-01, IAM-04) over the configuration. | N45: Automated (continuous) | O45: =IFERROR(INDEX('Sampling Guide'!$B$2:$B$20,MATCH(N45,'Sampling Guide'!$A$2:$A$20,0)),"TBD") -> 1
A46: INF-04 | B46: Infrastructure | C46: Encryption in transit | D46: External and internal service traffic uses TLS 1.2+; weak ciphers are disabled. | E46: CLD, K8S | F46: Preventive | G46: Automated | H46: Continuous | I46: Platform Engineering | J46: CC6.7, CC6.1 | K46: Load balancer TLS policy; TLS scan results | L46: Scheduled external TLS scan | M46: 1) Inquire of Platform Engineering to understand the control. 2) Inspect the configuration in CLD, K8S at a point in time. 3) Inspect change/drift history to confirm the configuration was in effect throughout the period. 4) Where feasible, re-perform (attempt a prohibited action) and observe it is blocked or alerted. 5) Rely on ITGCs (CHG-01, IAM-04) over the configuration. | N46: Automated (continuous) | O46: =IFERROR(INDEX('Sampling Guide'!$B$2:$B$20,MATCH(N46,'Sampling Guide'!$A$2:$A$20,0)),"TBD") -> 1
A47: INF-05 | B47: Infrastructure | C47: Encryption at rest and key management | D47: Production data stores, backups and volumes are encrypted at rest using managed KMS keys; key access is restricted and key usage logged. | E47: CLD, VAULT | F47: Preventive | G47: Automated | H47: Continuous | I47: Platform Engineering | J47: CC6.1, CC6.7 | K47: Encryption settings export; KMS key policies | L47: CSPM rule for unencrypted storage | M47: 1) Inquire of Platform Engineering to understand the control. 2) Inspect the configuration in CLD, VAULT at a point in time. 3) Inspect change/drift history to confirm the configuration was in effect throughout the period. 4) Where feasible, re-perform (attempt a prohibited action) and observe it is blocked or alerted. 5) Rely on ITGCs (CHG-01, IAM-04) over the configuration. | N47: Automated (continuous) | O47: =IFERROR(INDEX('Sampling Guide'!$B$2:$B$20,MATCH(N47,'Sampling Guide'!$A$2:$A$20,0)),"TBD") -> 1
A48: INF-06 | B48: Infrastructure | C48: Secrets management | D48: Application and pipeline secrets are stored in a secrets manager, injected at runtime, and never committed to source; secret scanning is enforced with push protection. | E48: VAULT, SCM, CI | F48: Preventive | G48: Automated | H48: Continuous | I48: Platform Engineering | J48: CC6.1, CC6.7 | K48: Secrets manager config; push-protection setting; scanning alerts | L48: SCM secret-scanning alerts exported | M48: 1) Inquire of Platform Engineering to understand the control. 2) Inspect the configuration in VAULT, SCM, CI at a point in time. 3) Inspect change/drift history to confirm the configuration was in effect throughout the period. 4) Where feasible, re-perform (attempt a prohibited action) and observe it is blocked or alerted. 5) Rely on ITGCs (CHG-01, IAM-04) over the configuration. | N48: Automated (continuous) | O48: =IFERROR(INDEX('Sampling Guide'!$B$2:$B$20,MATCH(N48,'Sampling Guide'!$A$2:$A$20,0)),"TBD") -> 1 | Q48: GitHub secret scanning + push protection (delegated bypass → Security); secrets only as environment secrets
A49: INF-07 | B49: Infrastructure | C49: Asset inventory | D49: An inventory of cloud resources, endpoints, repositories and SaaS applications is maintained automatically and reviewed quarterly. | E49: CLD, MDM, SCM, IDP, GRC | F49: Detective | G49: Automated | H49: Continuous / Quarterly review | I49: IT / Platform Engineering | J49: CC6.1, CC2.1, CC3.2 | K49: Inventory exports; quarterly review record | L49: Collectors pull cloud asset, MDM and SCM repo lists nightly | M49: 1) Inquire of IT / Platform Engineering to understand the control. 2) Inspect the configuration in CLD, MDM, SCM, IDP, GRC at a point in time. 3) Inspect change/drift history to confirm the configuration was in effect throughout the period. 4) Where feasible, re-perform (attempt a prohibited action) and observe it is blocked or alerted. 5) Rely on ITGCs (CHG-01, IAM-04) over the configuration. | N49: Automated (continuous) | O49: =IFERROR(INDEX('Sampling Guide'!$B$2:$B$20,MATCH(N49,'Sampling Guide'!$A$2:$A$20,0)),"TBD") -> 1
A50: INF-08 | B50: Infrastructure | C50: Endpoint security | D50: Company endpoints are enrolled in MDM with disk encryption, screen lock, OS updates and EDR/anti-malware enforced; non-compliant devices are blocked from SSO. | E50: MDM, IDP | F50: Preventive | G50: Automated | H50: Continuous | I50: IT / Identity Admin | J50: CC6.8, CC6.1, CC6.7 | K50: MDM compliance report; device-trust policy in IdP | L50: MDM compliance export weekly | M50: 1) Inquire of IT / Identity Admin to understand the control. 2) Inspect the configuration in MDM, IDP at a point in time. 3) Inspect change/drift history to confirm the configuration was in effect throughout the period. 4) Where feasible, re-perform (attempt a prohibited action) and observe it is blocked or alerted. 5) Rely on ITGCs (CHG-01, IAM-04) over the configuration. | N50: Automated (continuous) | O50: =IFERROR(INDEX('Sampling Guide'!$B$2:$B$20,MATCH(N50,'Sampling Guide'!$A$2:$A$20,0)),"TBD") -> 1
A51: INF-09 | B51: Infrastructure | C51: Data disposal and media sanitization | D51: Customer data is deleted per contract/retention schedule; decommissioned endpoints are wiped; cloud provider media destruction relied upon via CUEC/sub-service SOC report. | E51: CLD, MDM, ITSM | F51: Preventive | G51: IT-dependent manual | H51: Per event | I51: IT / Platform Engineering | J51: CC6.5 | K51: Deletion tickets/logs; device wipe records; cloud provider SOC 2 review | L51: MDM wipe logs | M51: 1) Inquire of IT / Platform Engineering. 2) Obtain the complete population of occurrences for the period and verify completeness (system-generated list). 3) Select a sample per the Sampling Guide. 4) Inspect evidence (Deletion tickets/logs) for performance, timeliness, reviewer independence and follow-up of exceptions. | N51: Per event / multiple times per day | O51: =IFERROR(INDEX('Sampling Guide'!$B$2:$B$20,MATCH(N51,'Sampling Guide'!$A$2:$A$20,0)),"TBD") -> 25
A52: INF-10 | B52: Infrastructure | C52: Physical security (carved-out) | D52: Physical security of data centers is the responsibility of the cloud provider (sub-service organization, carve-out); office access is badge-controlled where applicable. | E52: CLD, GRC | F52: Preventive | G52: Manual | H52: Annual | I52: Compliance Manager | J52: CC6.4 | K52: Cloud provider SOC 2 review memo; office access procedure | L52: n/a | M52: 1) Inquire of Compliance Manager. 2) Obtain the complete population of occurrences for the period and verify completeness (system-generated list). 3) Select a sample per the Sampling Guide. 4) Inspect evidence (Cloud provider SOC 2 review memo) for performance, timeliness, reviewer independence and follow-up of exceptions. | N52: Annual | O52: =IFERROR(INDEX('Sampling Guide'!$B$2:$B$20,MATCH(N52,'Sampling Guide'!$A$2:$A$20,0)),"TBD") -> 1
A53: INF-11 | B53: Infrastructure | C53: Data loss prevention / egress restrictions | D53: Transfer of confidential data outside approved systems is restricted (egress controls, storage bucket public-access blocks, DLP on email/SaaS where applicable). | E53: CLD, MDM, IDP | F53: Preventive | G53: Automated | H53: Continuous | I53: CISO / Security Lead | J53: CC6.7 | K53: Public access block config; egress rules; DLP policy | L53: CSPM rule for public buckets | M53: 1) Inquire of CISO / Security Lead to understand the control. 2) Inspect the configuration in CLD, MDM, IDP at a point in time. 3) Inspect change/drift history to confirm the configuration was in effect throughout the period. 4) Where feasible, re-perform (attempt a prohibited action) and observe it is blocked or alerted. 5) Rely on ITGCs (CHG-01, IAM-04) over the configuration. | N53: Automated (continuous) | O53: =IFERROR(INDEX('Sampling Guide'!$B$2:$B$20,MATCH(N53,'Sampling Guide'!$A$2:$A$20,0)),"TBD") -> 1
A54: VUL-01 | B54: Vulnerability Management | C54: Vulnerability scanning | D54: Infrastructure, container images and dependencies are scanned at least weekly and on build; findings are triaged and remediated within SLA (Critical 7d, High 30d, Medium 90d). | E54: SEC, REG, CLD, ITSM | F54: Detective | G54: Automated | H54: Weekly / Per build | I54: AppSec Lead | J54: CC7.1, CC6.8 | K54: Scan reports; SLA compliance report; remediation tickets | L54: Scanner -> ITSM auto-ticketing with SLA fields | M54: 1) Inquire of AppSec Lead to understand the control. 2) Inspect the configuration in SEC, REG, CLD, ITSM at a point in time. 3) Inspect change/drift history to confirm the configuration was in effect throughout the period. 4) Where feasible, re-perform (attempt a prohibited action) and observe it is blocked or alerted. 5) Rely on ITGCs (CHG-01, IAM-04) over the configuration. | N54: Weekly | O54: =IFERROR(INDEX('Sampling Guide'!$B$2:$B$20,MATCH(N54,'Sampling Guide'!$A$2:$A$20,0)),"TBD") -> 5 | Q54: GitHub code-scanning / Dependabot / secret-scanning alerts → ServiceNow (Vulnerability Response or incident) with SLA definitions
A55: VUL-02 | B55: Vulnerability Management | C55: Annual penetration test | D55: An independent penetration test of the production application and infrastructure is performed annually; findings are remediated within SLA. | E55: SEC, ITSM | F55: Detective | G55: Manual | H55: Annual | I55: AppSec Lead | J55: CC7.1, CC4.1 | K55: Pen test report; remediation tickets / retest letter | L55: n/a | M55: 1) Inquire of AppSec Lead. 2) Obtain the complete population of occurrences for the period and verify completeness (system-generated list). 3) Select a sample per the Sampling Guide. 4) Inspect evidence (Pen test report) for performance, timeliness, reviewer independence and follow-up of exceptions. | N55: Annual | O55: =IFERROR(INDEX('Sampling Guide'!$B$2:$B$20,MATCH(N55,'Sampling Guide'!$A$2:$A$20,0)),"TBD") -> 1
A56: VUL-03 | B56: Vulnerability Management | C56: Patch management | D56: OS and runtime patches are applied through rebuilt images deployed via pipeline; managed services patched by provider. | E56: CI, REG, CLD | F56: Preventive | G56: Automated | H56: Monthly | I56: Platform Engineering | J56: CC7.1 | K56: Base image rebuild logs; image age report | L56: Report of running images older than 30 days | M56: 1) Inquire of Platform Engineering to understand the control. 2) Inspect the configuration in CI, REG, CLD at a point in time. 3) Inspect change/drift history to confirm the configuration was in effect throughout the period. 4) Where feasible, re-perform (attempt a prohibited action) and observe it is blocked or alerted. 5) Rely on ITGCs (CHG-01, IAM-04) over the configuration. | N56: Monthly | O56: =IFERROR(INDEX('Sampling Guide'!$B$2:$B$20,MATCH(N56,'Sampling Guide'!$A$2:$A$20,0)),"TBD") -> 2
A57: MON-01 | B57: Logging & Monitoring | C57: Centralized audit logging | D57: Audit logs from IdP, SCM, CI/CD, cloud control plane, Kubernetes API, and ITSM are forwarded to the SIEM; log sources are monitored for ingestion gaps. | E57: SIEM, IDP, SCM, CI, CLD, K8S, ITSM | F57: Detective | G57: Automated | H57: Continuous | I57: Security Operations | J57: CC7.2, CC4.1, CC2.1 | K57: Log source inventory with last-seen timestamps; forwarding configs | L57: SIEM health check alerts when a source is silent >1h | M57: 1) Inquire of Security Operations to understand the control. 2) Inspect the configuration in SIEM, IDP, SCM, CI, CLD, K8S, ITSM at a point in time. 3) Inspect change/drift history to confirm the configuration was in effect throughout the period. 4) Where feasible, re-perform (attempt a prohibited action) and observe it is blocked or alerted. 5) Rely on ITGCs (CHG-01, IAM-04) over the configuration. | N57: Automated (continuous) | O57: =IFERROR(INDEX('Sampling Guide'!$B$2:$B$20,MATCH(N57,'Sampling Guide'!$A$2:$A$20,0)),"TBD") -> 1 | Q57: GitHub enterprise audit-log streaming (incl. Git & API events) → SIEM; ServiceNow log export → SIEM
A58: MON-02 | B58: Logging & Monitoring | C58: Log integrity and retention | D58: Logs are stored immutably (WORM/object lock) and retained at least 12 months (90 days hot). | E58: SIEM, CLD | F58: Preventive | G58: Automated | H58: Continuous | I58: Security Operations | J58: CC7.2, CC6.1 | K58: Retention and object-lock configuration | L58: Config export | M58: 1) Inquire of Security Operations to understand the control. 2) Inspect the configuration in SIEM, CLD at a point in time. 3) Inspect change/drift history to confirm the configuration was in effect throughout the period. 4) Where feasible, re-perform (attempt a prohibited action) and observe it is blocked or alerted. 5) Rely on ITGCs (CHG-01, IAM-04) over the configuration. | N58: Automated (continuous) | O58: =IFERROR(INDEX('Sampling Guide'!$B$2:$B$20,MATCH(N58,'Sampling Guide'!$A$2:$A$20,0)),"TBD") -> 1
A59: MON-03 | B59: Logging & Monitoring | C59: Security alerting rules | D59: Detection rules alert on high-risk events: MFA/branch-protection disabled, admin role grants, break-glass use, pipeline secret access anomalies, public exposure, impossible travel. | E59: SIEM, ONC | F59: Detective | G59: Automated | H59: Continuous | I59: Security Operations | J59: CC7.2, CC7.3 | K59: Detection rule catalog; sample alerts and triage tickets | L59: Rules managed as code (detection-as-code repo) | M59: 1) Inquire of Security Operations to understand the control. 2) Inspect the configuration in SIEM, ONC at a point in time. 3) Inspect change/drift history to confirm the configuration was in effect throughout the period. 4) Where feasible, re-perform (attempt a prohibited action) and observe it is blocked or alerted. 5) Rely on ITGCs (CHG-01, IAM-04) over the configuration. | N59: Automated (continuous) | O59: =IFERROR(INDEX('Sampling Guide'!$B$2:$B$20,MATCH(N59,'Sampling Guide'!$A$2:$A$20,0)),"TBD") -> 1 | Q59: Detections on GitHub audit events (repository_ruleset.*, protected_branch.policy_override, environment protection changes) and ServiceNow admin/approval events
A60: MON-04 | B60: Logging & Monitoring | C60: Availability and performance monitoring | D60: Production services are monitored for availability, errors and latency; alerts route to on-call with escalation. | E60: MON, ONC | F60: Detective | G60: Automated | H60: Continuous | I60: SRE Lead | J60: CC7.2, CC9.1 | K60: Monitor/alert definitions; on-call schedule; paging history | L60: Monitors defined as code | M60: 1) Inquire of SRE Lead to understand the control. 2) Inspect the configuration in MON, ONC at a point in time. 3) Inspect change/drift history to confirm the configuration was in effect throughout the period. 4) Where feasible, re-perform (attempt a prohibited action) and observe it is blocked or alerted. 5) Rely on ITGCs (CHG-01, IAM-04) over the configuration. | N60: Automated (continuous) | O60: =IFERROR(INDEX('Sampling Guide'!$B$2:$B$20,MATCH(N60,'Sampling Guide'!$A$2:$A$20,0)),"TBD") -> 1
A61: MON-05 | B61: Logging & Monitoring | C61: Alert triage and ticketing | D61: Security alerts are triaged within defined SLAs; triage outcome is documented in a ticket. | E61: SIEM, ITSM, ONC | F61: Detective | G61: IT-dependent manual | H61: Per event | I61: Security Operations | J61: CC7.3 | K61: Alert-to-ticket linkage; triage timestamps for sampled alerts | L61: SIEM -> ITSM integration | M61: 1) Inquire of Security Operations. 2) Obtain the complete population of occurrences for the period and verify completeness (system-generated list). 3) Select a sample per the Sampling Guide. 4) Inspect evidence (Alert-to-ticket linkage) for performance, timeliness, reviewer independence and follow-up of exceptions. | N61: Per event / multiple times per day | O61: =IFERROR(INDEX('Sampling Guide'!$B$2:$B$20,MATCH(N61,'Sampling Guide'!$A$2:$A$20,0)),"TBD") -> 25 | Q61: SIEM → ServiceNow incident / Security Incident Response
A62: MON-06 | B62: Logging & Monitoring | C62: Control-drift monitoring (continuous compliance) | D62: Automated checks verify key controls (SSO enforcement, branch protection, MFA, encryption, logging) daily; failures alert control owners and are tracked. | E62: GRC, SCM, IDP, CLD | F62: Detective | G62: Automated | H62: Daily | I62: Compliance Manager | J62: CC4.1, CC4.2, CC5.2 | K62: Control check results history; failure tickets | L62: Evidence collectors + policy engine | M62: 1) Inquire of Compliance Manager to understand the control. 2) Inspect the configuration in GRC, SCM, IDP, CLD at a point in time. 3) Inspect change/drift history to confirm the configuration was in effect throughout the period. 4) Where feasible, re-perform (attempt a prohibited action) and observe it is blocked or alerted. 5) Rely on ITGCs (CHG-01, IAM-04) over the configuration. | N62: Daily | O62: =IFERROR(INDEX('Sampling Guide'!$B$2:$B$20,MATCH(N62,'Sampling Guide'!$A$2:$A$20,0)),"TBD") -> 20
A63: IR-01 | B63: Incident Response | C63: Incident response plan | D63: An incident response plan defines roles, severity levels, communication, evidence preservation and notification obligations; reviewed annually. | E63: GRC | F63: Preventive | G63: Manual | H63: Annual | I63: CISO / Security Lead | J63: CC7.3, CC7.4, CC7.5, CC2.3 | K63: Approved IR plan with review date | L63: n/a | M63: 1) Inquire of CISO / Security Lead. 2) Obtain the complete population of occurrences for the period and verify completeness (system-generated list). 3) Select a sample per the Sampling Guide. 4) Inspect evidence (Approved IR plan with review date) for performance, timeliness, reviewer independence and follow-up of exceptions. | N63: Annual | O63: =IFERROR(INDEX('Sampling Guide'!$B$2:$B$20,MATCH(N63,'Sampling Guide'!$A$2:$A$20,0)),"TBD") -> 1
A64: IR-02 | B64: Incident Response | C64: Incident tracking and response | D64: Security incidents are logged, classified, tracked to resolution and communicated per the IR plan, including customer notification when required. | E64: ITSM, ONC | F64: Corrective | G64: IT-dependent manual | H64: Per event | I64: CISO / Security Lead | J64: CC7.3, CC7.4, CC2.3 | K64: Incident tickets with timeline, severity, notifications | L64: Incident tooling timeline export | M64: 1) Inquire of CISO / Security Lead. 2) Obtain the complete population of occurrences for the period and verify completeness (system-generated list). 3) Select a sample per the Sampling Guide. 4) Inspect evidence (Incident tickets with timeline, severity, notifications) for performance, timeliness, reviewer independence and follow-up of exceptions. | N64: Per event / multiple times per day | O64: =IFERROR(INDEX('Sampling Guide'!$B$2:$B$20,MATCH(N64,'Sampling Guide'!$A$2:$A$20,0)),"TBD") -> 25 | Q64: ServiceNow Security Incident Response (or incident category=Security, P1–P2)
A65: IR-03 | B65: Incident Response | C65: Post-incident review | D65: Sev1/Sev2 incidents receive a blameless post-incident review with corrective actions tracked to closure. | E65: ITSM | F65: Corrective | G65: Manual | H65: Per event | I65: CISO / Security Lead | J65: CC7.4, CC7.5, CC4.2 | K65: Post-incident reports; corrective action tickets | L65: n/a | M65: 1) Inquire of CISO / Security Lead. 2) Obtain the complete population of occurrences for the period and verify completeness (system-generated list). 3) Select a sample per the Sampling Guide. 4) Inspect evidence (Post-incident reports) for performance, timeliness, reviewer independence and follow-up of exceptions. | N65: Per event / multiple times per day | O65: =IFERROR(INDEX('Sampling Guide'!$B$2:$B$20,MATCH(N65,'Sampling Guide'!$A$2:$A$20,0)),"TBD") -> 25 | Q65: ServiceNow problem / PIR record linked to incident
A66: IR-04 | B66: Incident Response | C66: Annual IR tabletop exercise | D66: An incident response tabletop exercise is conducted at least annually; lessons learned update the plan. | E66: GRC | F66: Detective | G66: Manual | H66: Annual | I66: CISO / Security Lead | J66: CC7.4, CC7.5 | K66: Tabletop report with attendees and outcomes | L66: n/a | M66: 1) Inquire of CISO / Security Lead. 2) Obtain the complete population of occurrences for the period and verify completeness (system-generated list). 3) Select a sample per the Sampling Guide. 4) Inspect evidence (Tabletop report with attendees and outcomes) for performance, timeliness, reviewer independence and follow-up of exceptions. | N66: Annual | O66: =IFERROR(INDEX('Sampling Guide'!$B$2:$B$20,MATCH(N66,'Sampling Guide'!$A$2:$A$20,0)),"TBD") -> 1
A67: BCP-01 | B67: Business Continuity | C67: Automated backups | D67: Production databases and critical data stores are backed up automatically per defined RPO; backups are encrypted and stored in a separate account/region. | E67: BKP, CLD | F67: Preventive | G67: Automated | H67: Daily | I67: SRE Lead | J67: CC7.5, CC9.1 | K67: Backup policy configuration; backup job success report | L67: Backup job status exported daily; failures alert on-call | M67: 1) Inquire of SRE Lead to understand the control. 2) Inspect the configuration in BKP, CLD at a point in time. 3) Inspect change/drift history to confirm the configuration was in effect throughout the period. 4) Where feasible, re-perform (attempt a prohibited action) and observe it is blocked or alerted. 5) Rely on ITGCs (CHG-01, IAM-04) over the configuration. | N67: Daily | O67: =IFERROR(INDEX('Sampling Guide'!$B$2:$B$20,MATCH(N67,'Sampling Guide'!$A$2:$A$20,0)),"TBD") -> 20
A68: BCP-02 | B68: Business Continuity | C68: Backup restoration test | D68: Restores from backup are tested at least quarterly and results documented against RTO/RPO. | E68: BKP, ITSM | F68: Detective | G68: Manual | H68: Quarterly | I68: SRE Lead | J68: CC7.5, CC9.1 | K68: Restore test tickets with results and timings | L68: n/a | M68: 1) Inquire of SRE Lead. 2) Obtain the complete population of occurrences for the period and verify completeness (system-generated list). 3) Select a sample per the Sampling Guide. 4) Inspect evidence (Restore test tickets with results and timings) for performance, timeliness, reviewer independence and follow-up of exceptions. | N68: Quarterly | O68: =IFERROR(INDEX('Sampling Guide'!$B$2:$B$20,MATCH(N68,'Sampling Guide'!$A$2:$A$20,0)),"TBD") -> 2
A69: BCP-03 | B69: Business Continuity | C69: BC/DR plan and annual test | D69: A BC/DR plan with RTO/RPO for critical services is maintained and tested annually (failover or tabletop). | E69: GRC | F69: Corrective | G69: Manual | H69: Annual | I69: SRE Lead | J69: CC7.5, CC9.1 | K69: BC/DR plan; DR test report | L69: n/a | M69: 1) Inquire of SRE Lead. 2) Obtain the complete population of occurrences for the period and verify completeness (system-generated list). 3) Select a sample per the Sampling Guide. 4) Inspect evidence (BC/DR plan) for performance, timeliness, reviewer independence and follow-up of exceptions. | N69: Annual | O69: =IFERROR(INDEX('Sampling Guide'!$B$2:$B$20,MATCH(N69,'Sampling Guide'!$A$2:$A$20,0)),"TBD") -> 1
A70: BCP-04 | B70: Business Continuity | C70: Resilient architecture | D70: Production is deployed across multiple availability zones with health checks and auto-recovery; infrastructure can be rebuilt from IaC. | E70: CLD, K8S, IAC | F70: Preventive | G70: Automated | H70: Continuous | I70: Platform Engineering | J70: CC9.1, CC7.5 | K70: Architecture diagram; multi-AZ config export | L70: IaC export | M70: 1) Inquire of Platform Engineering to understand the control. 2) Inspect the configuration in CLD, K8S, IAC at a point in time. 3) Inspect change/drift history to confirm the configuration was in effect throughout the period. 4) Where feasible, re-perform (attempt a prohibited action) and observe it is blocked or alerted. 5) Rely on ITGCs (CHG-01, IAM-04) over the configuration. | N70: Automated (continuous) | O70: =IFERROR(INDEX('Sampling Guide'!$B$2:$B$20,MATCH(N70,'Sampling Guide'!$A$2:$A$20,0)),"TBD") -> 1

Sheet TSC Coverage
A1: Criterion | B1: Category | C1: Summary (paraphrased) | D1: # Mapped Controls | E1: # Implemented | F1: Design Coverage | G1: Readiness
A2: CC1.1 | B2: Control Environment | C2: Demonstrates commitment to integrity and ethical values | D2: =COUNTIF('Control Matrix'!$J$2:$J$70,"*"&A2&"*") -> 3 | E2: =COUNTIFS('Control Matrix'!$J$2:$J$70,"*"&A2&"*",'Control Matrix'!$R$2:$R$70,"Implemented") -> 1 | F2: =IF(D2>0,"Covered","GAP") -> Covered | G2: =IF(D2=0,"GAP",IF(E2=D2,"Ready",IF(E2>0,"In progress","Not started"))) -> In progress
A3: CC1.2 | B3: Control Environment | C3: Board exercises oversight responsibility, independent of management | D3: =COUNTIF('Control Matrix'!$J$2:$J$70,"*"&A3&"*") -> 1 | E3: =COUNTIFS('Control Matrix'!$J$2:$J$70,"*"&A3&"*",'Control Matrix'!$R$2:$R$70,"Implemented") -> 0 | F3: =IF(D3>0,"Covered","GAP") -> Covered | G3: =IF(D3=0,"GAP",IF(E3=D3,"Ready",IF(E3>0,"In progress","Not started"))) -> Not started
A4: CC1.3 | B4: Control Environment | C4: Management establishes structures, reporting lines, authorities and responsibilities | D4: =COUNTIF('Control Matrix'!$J$2:$J$70,"*"&A4&"*") -> 3 | E4: =COUNTIFS('Control Matrix'!$J$2:$J$70,"*"&A4&"*",'Control Matrix'!$R$2:$R$70,"Implemented") -> 0 | F4: =IF(D4>0,"Covered","GAP") -> Covered | G4: =IF(D4=0,"GAP",IF(E4=D4,"Ready",IF(E4>0,"In progress","Not started"))) -> Not started
A5: CC1.4 | B5: Control Environment | C5: Demonstrates commitment to attract, develop and retain competent individuals | D5: =COUNTIF('Control Matrix'!$J$2:$J$70,"*"&A5&"*") -> 3 | E5: =COUNTIFS('Control Matrix'!$J$2:$J$70,"*"&A5&"*",'Control Matrix'!$R$2:$R$70,"Implemented") -> 0 | F5: =IF(D5>0,"Covered","GAP") -> Covered | G5: =IF(D5=0,"GAP",IF(E5=D5,"Ready",IF(E5>0,"In progress","Not started"))) -> Not started
A6: CC1.5 | B6: Control Environment | C6: Holds individuals accountable for internal control responsibilities | D6: =COUNTIF('Control Matrix'!$J$2:$J$70,"*"&A6&"*") -> 3 | E6: =COUNTIFS('Control Matrix'!$J$2:$J$70,"*"&A6&"*",'Control Matrix'!$R$2:$R$70,"Implemented") -> 0 | F6: =IF(D6>0,"Covered","GAP") -> Covered | G6: =IF(D6=0,"GAP",IF(E6=D6,"Ready",IF(E6>0,"In progress","Not started"))) -> Not started
A7: CC2.1 | B7: Communication & Information | C7: Obtains/generates and uses relevant, quality information | D7: =COUNTIF('Control Matrix'!$J$2:$J$70,"*"&A7&"*") -> 5 | E7: =COUNTIFS('Control Matrix'!$J$2:$J$70,"*"&A7&"*",'Control Matrix'!$R$2:$R$70,"Implemented") -> 0 | F7: =IF(D7>0,"Covered","GAP") -> Covered | G7: =IF(D7=0,"GAP",IF(E7=D7,"Ready",IF(E7>0,"In progress","Not started"))) -> Not started
A8: CC2.2 | B8: Communication & Information | C8: Internally communicates objectives and responsibilities for internal control | D8: =COUNTIF('Control Matrix'!$J$2:$J$70,"*"&A8&"*") -> 4 | E8: =COUNTIFS('Control Matrix'!$J$2:$J$70,"*"&A8&"*",'Control Matrix'!$R$2:$R$70,"Implemented") -> 1 | F8: =IF(D8>0,"Covered","GAP") -> Covered | G8: =IF(D8=0,"GAP",IF(E8=D8,"Ready",IF(E8>0,"In progress","Not started"))) -> In progress
A9: CC2.3 | B9: Communication & Information | C9: Communicates with external parties regarding internal control matters | D9: =COUNTIF('Control Matrix'!$J$2:$J$70,"*"&A9&"*") -> 5 | E9: =COUNTIFS('Control Matrix'!$J$2:$J$70,"*"&A9&"*",'Control Matrix'!$R$2:$R$70,"Implemented") -> 0 | F9: =IF(D9>0,"Covered","GAP") -> Covered | G9: =IF(D9=0,"GAP",IF(E9=D9,"Ready",IF(E9>0,"In progress","Not started"))) -> Not started
A10: CC3.1 | B10: Risk Assessment | C10: Specifies objectives with sufficient clarity to identify and assess risks | D10: =COUNTIF('Control Matrix'!$J$2:$J$70,"*"&A10&"*") -> 2 | E10: =COUNTIFS('Control Matrix'!$J$2:$J$70,"*"&A10&"*",'Control Matrix'!$R$2:$R$70,"Implemented") -> 0 | F10: =IF(D10>0,"Covered","GAP") -> Covered | G10: =IF(D10=0,"GAP",IF(E10=D10,"Ready",IF(E10>0,"In progress","Not started"))) -> Not started
A11: CC3.2 | B11: Risk Assessment | C11: Identifies and analyzes risks to the achievement of objectives | D11: =COUNTIF('Control Matrix'!$J$2:$J$70,"*"&A11&"*") -> 2 | E11: =COUNTIFS('Control Matrix'!$J$2:$J$70,"*"&A11&"*",'Control Matrix'!$R$2:$R$70,"Implemented") -> 0 | F11: =IF(D11>0,"Covered","GAP") -> Covered | G11: =IF(D11=0,"GAP",IF(E11=D11,"Ready",IF(E11>0,"In progress","Not started"))) -> Not started
A12: CC3.3 | B12: Risk Assessment | C12: Considers the potential for fraud in assessing risks | D12: =COUNTIF('Control Matrix'!$J$2:$J$70,"*"&A12&"*") -> 1 | E12: =COUNTIFS('Control Matrix'!$J$2:$J$70,"*"&A12&"*",'Control Matrix'!$R$2:$R$70,"Implemented") -> 0 | F12: =IF(D12>0,"Covered","GAP") -> Covered | G12: =IF(D12=0,"GAP",IF(E12=D12,"Ready",IF(E12>0,"In progress","Not started"))) -> Not started
A13: CC3.4 | B13: Risk Assessment | C13: Identifies and assesses changes that could significantly impact internal control | D13: =COUNTIF('Control Matrix'!$J$2:$J$70,"*"&A13&"*") -> 4 | E13: =COUNTIFS('Control Matrix'!$J$2:$J$70,"*"&A13&"*",'Control Matrix'!$R$2:$R$70,"Implemented") -> 0 | F13: =IF(D13>0,"Covered","GAP") -> Covered | G13: =IF(D13=0,"GAP",IF(E13=D13,"Ready",IF(E13>0,"In progress","Not started"))) -> Not started
... A34: CC9.2 | B34: Risk Mitigation | C34: Assesses and manages risks associated with vendors and business partners | D34: =COUNTIF('Control Matrix'!$J$2:$J$70,"*"&A34&"*") -> 3 | E34: =COUNTIFS('Control Matrix'!$J$2:$J$70,"*"&A34&"*",'Control Matrix'!$R$2:$R$70,"Implemented") -> 0 | F34: =IF(D34>0,"Covered","GAP") -> Covered | G34: =IF(D34=0,"GAP",IF(E34=D34,"Ready",IF(E34>0,"In progress","Not started"))) -> Not started
A36: Mapped control IDs (static reference, generated at build):
A37: CC1.1 | B37: GOV-01, GOV-07, HR-02
A38: CC1.2 | B38: GOV-02
A39: CC1.3 | B39: GOV-03, GOV-04, HR-04
A40: CC1.4 | B40: HR-01, HR-03, HR-04
A41: CC1.5 | B41: HR-02, HR-04, HR-05
A42: CC2.1 | B42: GOV-04, GOV-08, CHG-06, INF-07, MON-01
A43: CC2.2 | B43: GOV-01, GOV-07, HR-02, HR-03
A44: CC2.3 | B44: GOV-06, GOV-07, VEN-02, IR-01, IR-02
A45: CC3.1 | B45: RSK-01, RSK-02
A46: CC3.2 | B46: RSK-01, INF-07
A47: CC3.3 | B47: RSK-01
A48: CC3.4 | B48: GOV-08, RSK-01, RSK-03, CHG-12
... A69: CC9.2 | B69: VEN-01, VEN-02, VEN-03

Sheet Integration Inventory
A1: Code | B1: Subsystem | C1: Category | D1: Example Tools (vendor-neutral) | E1: Your Tool | F1: Identity / Auth Integration | G1: Audit Log Export | H1: Integrates With | I1: Data Handled (Classification) | J1: Evidence Produced | K1: Key Controls | L1: System Owner
A2: SCM | B2: Source Control | C2: CI/CD | D2: e.g., GitHub, GitLab, Bitbucket | E2: GitHub Enterprise Cloud | F2: SAML/OIDC SSO via IdP + SCIM; enforce SSO for org | G2: Audit log streaming to SIEM (webhook / streaming API) | H2: CI, SEC, ITSM, IDP, SIEM | I2: Source code, IaC, pipeline definitions (Confidential) | J2: Rulesets, merged PR + review data, CODEOWNERS, secret-scanning alerts | K2: CHG-01, CHG-02, CHG-11, INF-06, IAM-01
A3: CI | B3: CI/CD Pipeline | C3: CI/CD | D3: e.g., GitHub Actions, GitLab CI, Jenkins, Argo CD | E3: GitHub Actions | F3: SSO via IdP; deploy via OIDC workload identity to cloud | G3: Run logs + audit events to SIEM; deployment records to evidence store | H3: SCM, REG, CLD, K8S, VAULT, SEC, ITSM | I3: Build artifacts, deploy metadata, secrets at runtime (Restricted) | J3: Pipeline run logs, gate results, deployment records (SHA->PR->run->digest) | K3: CHG-03 to CHG-07, CHG-10, CHG-11
A4: REG | B4: Artifact Registry | C4: CI/CD | D4: e.g., ECR, Artifact Registry, ACR, Harbor, JFrog | F4: Pull/push by workload identity; humans read-only via SSO | G4: Registry audit events to SIEM | H4: CI, K8S, SEC | I4: Container images, packages (Confidential) | J4: Image signatures, provenance attestations, scan results | K4: CHG-07, VUL-01, VUL-03
A5: CLD | B5: Cloud Platform | C5: Infrastructure | D5: e.g., AWS, Azure, GCP | F5: Federated SSO from IdP to roles; no IAM users; OIDC for CI | G5: Control-plane audit logs (e.g., CloudTrail / Activity Log / Audit Logs) org-wide to log archive + SIEM | H5: IAC, CI, K8S, SIEM, BKP, VAULT, SEC | I5: Production customer data (Restricted) | J5: IAM exports, config/asset inventory, encryption settings, audit logs | K5: IAM-05, CHG-05, CHG-08, INF-01 to INF-05, BCP-04
A6: IAC | B6: IaC / Config Mgmt | C6: Infrastructure | D6: e.g., Terraform/OpenTofu, Pulumi, CloudFormation, Ansible | F6: Executed only by pipeline identity; state in encrypted remote backend | G6: Plan/apply logs archived by pipeline | H6: SCM, CI, CLD | I6: Infrastructure definitions, state files (Restricted) | J6: Plan outputs, apply logs, policy-as-code results | K6: CHG-10, INF-01, INF-03, IAM-05
A7: K8S | B7: Container Orchestration | C7: Infrastructure | D7: e.g., EKS, AKS, GKE, OpenShift | F7: OIDC to IdP groups for humans; workload identity for pods | G7: API server audit logs to SIEM | H7: CI, REG, CLD, SIEM, VAULT | I7: Running workloads, customer data in transit (Restricted) | J7: RBAC bindings, admission policy, audit logs | K7: CHG-07, INF-01, INF-03, IAM-05
A8: IDP | B8: Identity Provider | C8: Identity | D8: e.g., Okta, Microsoft Entra ID, Google Workspace, JumpCloud | F8: Admin console with phishing-resistant MFA; admin roles least-privileged | G8: System log to SIEM | H8: HRIS, all SSO apps (SCIM), MDM, SIEM | I8: Identities, group membership (Confidential) | J8: Auth policies, user/group exports, deprovisioning timestamps | K8: IAM-01 to IAM-04, IAM-08
A9: HRIS | B9: HRIS | C9: Identity | D9: e.g., Workday, BambooHR, Rippling, HiBob | F9: SSO via IdP | G9: Joiner/mover/leaver events to IdP; reports for audit | H9: IDP, LMS/GRC | I9: Employee PII (Confidential) | J9: Hire/term lists, background checks, acknowledgments, training | K9: HR-01 to HR-04, IAM-02, IAM-03
A10: SIEM | B10: Logging / SIEM | C10: Monitoring | D10: e.g., Splunk, Microsoft Sentinel, Elastic, Datadog Cloud SIEM, Panther | F10: SSO via IdP; RBAC for analysts | G10: Self-audit log retained; immutable archive | H10: All log sources, ONC, ITSM | I10: Security logs (Confidential) | J10: Source health, detection rules, alerts, retention config | K10: MON-01 to MON-03, MON-05
A11: MON | B11: Monitoring / APM | C11: Monitoring | D11: e.g., Datadog, Prometheus/Grafana, New Relic, Cloud-native monitoring | F11: SSO via IdP | G11: Monitor change audit trail | H11: CLD, K8S, ONC | I11: Telemetry (Internal) | J11: Monitor definitions, uptime history | K11: MON-04
A12: ONC | B12: On-call / Alerting | C12: Monitoring | D12: e.g., PagerDuty, Opsgenie, incident.io | F12: SSO via IdP | G12: Incident timeline export | H12: SIEM, MON, ITSM, chat | I12: Incident metadata (Internal) | J12: Schedules, escalation policies, paging history | K12: MON-04, IR-02
A13: ITSM | B13: Ticketing / ITSM | C13: Operations | D13: e.g., Jira, ServiceNow, Linear | E13: ServiceNow (ITSM + DevOps Change Velocity) | F13: SSO via IdP; workflow permissions by role | G13: Audit log / ticket history export | H13: SCM, CI, SIEM, ONC, SEC, GRC | I13: Change, access, incident records (Internal/Confidential) | J13: Access requests, change & emergency tickets, incident & remediation tickets | K13: IAM-02, CHG-09, IR-02, VUL-01
A14: SEC | B14: Security Scanning | C14: Security | D14: e.g., SAST, SCA, secret scanning, container & CSPM scanners | F14: SSO via IdP; API tokens scoped read-only | G14: Findings export to SIEM/ITSM | H14: SCM, CI, REG, CLD, ITSM | I14: Findings (Confidential) | J14: Scan results, SLA reports, exception approvals | K14: CHG-04, INF-02, VUL-01
A15: MDM | B15: Endpoint / MDM | C15: Endpoint | D15: e.g., Intune, Jamf, Kandji + EDR | F15: SSO via IdP; device-trust signal to IdP | G15: Device compliance export; EDR alerts to SIEM | H15: IDP, SIEM | I15: Device posture (Internal) | J15: Compliance report, encryption status, wipe logs | K15: INF-08, INF-09
A16: VAULT | B16: Secrets Manager | C16: Security | D16: e.g., HashiCorp Vault, AWS Secrets Manager, Azure Key Vault, GCP Secret Manager | F16: Workload identity for apps/pipelines; humans via SSO + JIT | G16: Access audit log to SIEM | H16: CI, K8S, CLD | I16: Secrets & keys (Restricted) | J16: Secret inventory, rotation age, access logs | K16: INF-06, IAM-07, IAM-09
A17: BKP | B17: Backup Service | C17: Resilience | D17: e.g., cloud-native snapshots, AWS Backup, Velero | F17: Service roles; backup vault in separate account with lock | G17: Job status to MON/SIEM | H17: CLD, K8S, MON | I17: Backup copies of production data (Restricted) | J17: Backup job reports, restore test results | K17: BCP-01, BCP-02
A18: GRC | B18: Evidence Store / GRC | C18: Compliance | D18: e.g., GRC platform or WORM object storage bucket + index | F18: SSO via IdP; write via collector identity only | G18: Access log; object versioning/lock | H18: All collectors, ITSM | I18: Audit evidence (Confidential) | J18: Timestamped, hashed evidence packages per control per period | K18: All controls (evidence repository)

Sheet GitHub-ServiceNow Config
A1: # | B1: Setting | C1: System | D1: Level | E1: Required Value | F1: How to Verify (API / UI) | G1: Controls | H1: Status | I1: Verified By / Date | J1: Notes
A2: 1 | B2: Identity model | C2: GitHub | D2: Enterprise | E2: EMU, or SAML SSO enforced + SCIM from IdP | F2: Enterprise settings export; SCIM Users API | G2: IAM-01, IAM-02
A3: 2 | B3: Enterprise owners | C3: GitHub | D3: Enterprise | E3: ≤3 named people; quarterly review | F3: Enterprise people export | G3: IAM-05, IAM-04
A4: 3 | B4: Classic PATs | C4: GitHub | D4: Enterprise/Org | E4: Blocked | F4: Org PAT policy screenshot / API | G4: IAM-07
A5: 4 | B5: Fine-grained PATs | C5: GitHub | D5: Org | E5: Approval required; max lifetime ≤90 days | F5: /orgs/{org}/personal-access-tokens | G5: IAM-07
A6: 5 | B6: GitHub App / OAuth app installs | C6: GitHub | D6: Org | E6: Owner approval; OAuth app restrictions on | F6: /orgs/{org}/installations | G6: IAM-07
A7: 6 | B7: Base repository permission | C7: GitHub | D7: Org | E7: No permission (or Read) | F7: /orgs/{org} default_repository_permission | G7: IAM-05
A8: 7 | B8: Repo creation, visibility change, deletion, transfer | C8: GitHub | D8: Org | E8: Owners only | F8: Org settings export | G8: IAM-05, INF-11
A9: 8 | B9: Private repository forking | C9: GitHub | D9: Org | E9: Disabled | F9: /orgs/{org} members_can_fork_private_repositories | G9: INF-11
A10: 9 | B10: Custom property soc2_scope | C10: GitHub | D10: Org | E10: Boolean, required, set true on all prod repos | F10: /orgs/{org}/properties/values | G10: GOV-08
A11: 10 | B11: Default-branch ruleset | C11: GitHub | D11: Org | E11: Per DES-002 §3.3; enforcement active; bypass list empty | F11: /orgs/{org}/rulesets/{id} | G11: CHG-01, CHG-02, CHG-03, CHG-04
A12: 11 | B12: Release tag ruleset | C12: GitHub | D12: Org | E12: Block deletion/update of refs/tags/v* | F12: /orgs/{org}/rulesets/{id} | G12: CHG-01
A13: 12 | B13: CODEOWNERS on .github/, infra/, deploy/ | C13: GitHub | D13: Repo | E13: Platform + Security owners | F13: File in each soc2_scope repo | G13: CHG-11
... A35: 34 | B35: Access request catalog item | C35: ServiceNow | D35: Service Catalog | E35: Manager + system-owner approval; fulfils IdP group | F35: Catalog item + workflow | G35: IAM-02
B37: Configured | C37: =COUNTIF(H2:H35,"Configured")&" of "&COUNTA(B2:B35) -> 0 of 34
B38: Detail: DES-002 GitHub, GitHub Actions & ServiceNow Integration Specification

Sheet Evidence Automation
A1: Collector Job | B1: Source Subsystem(s) | C1: Collection Method | D1: Frequency | E1: Output Artifact (evidence store path) | F1: Controls Supported | G1: Implemented? (Y/N) | H1: Last Successful Run
A2: col-idp-policy | B2: IDP | C2: REST API: auth policies, MFA factors, app SSO assignments | D2: Nightly | E2: idp/policies/<date>.json + diff | F2: IAM-01, IAM-08 | G2: Y | H2: 2026-01-15
A3: col-idp-users | B3: IDP, HRIS | C3: API: users, status, lastLogin, deactivated_at; HRIS terminations | D3: Daily | E3: iam/leaver-recon/<date>.csv; ticket if SLA breached | F3: IAM-02, IAM-03
A4: col-access-review | B4: IDP, SCM, CLD, CI, SIEM, ITSM | C4: API user & role listings per system; row counts for completeness | D4: Quarterly (1st business day) | E4: access-review/<Qn>/<system>.csv | F4: IAM-04
A5: col-scm-rulesets | B5: GitHub | C5: gh api /orgs/{org}/rulesets (+ /rulesets/{id}); /repos/{o}/{r}/rules/branches/main for soc2_scope repos; diff vs. baseline | D5: Nightly | E5: scm/rulesets/<date>.json + drift alert | F5: CHG-01, CHG-02
A6: col-scm-prs | B6: GitHub | C6: GraphQL search is:pr is:merged base:main merged:<range> → author, mergedBy, APPROVED reviewers, mergeCommit, check runs | D6: Daily | E6: scm/merged-prs/<yyyy-mm>.jsonl | F6: CHG-02, CHG-03
A7: col-deploys | B7: GitHub, ServiceNow | C7: /repos/{o}/{r}/deployments?environment=production + statuses; join ServiceNow change number; attestation reference | D7: Per deploy / daily | E7: deployments/<yyyy-mm>.jsonl | F7: CHG-05, CHG-06, CHG-07
A8: col-cloud-iam | B8: CLD | C8: API: roles, policies, users, access keys & ages; org SCP/policies | D8: Nightly | E8: cloud/iam/<date>.json | F8: IAM-05, IAM-07, CHG-05
A9: col-cloud-audit-query | B9: CLD, SIEM | C9: Saved search: production write API calls by non-pipeline principals | D9: Monthly | E9: cloud/non-pipeline-changes/<yyyy-mm>.csv | F9: CHG-05, MON-01
A10: col-cspm | B10: SEC, CLD | C10: CSPM API: benchmark score, open findings by severity, age | D10: Weekly | E10: cspm/<date>.json | F10: INF-01, INF-02, INF-05, INF-11
A11: col-vulns | B11: SEC, ITSM | C11: Scanner API + ITSM JQL: findings, SLA status | D11: Weekly | E11: vuln/sla/<date>.csv | F11: VUL-01, CHG-04
A12: col-siem-health | B12: SIEM | C12: Query: last event per log source; retention settings | D12: Daily | E12: siem/source-health/<date>.csv | F12: MON-01, MON-02
A13: col-mdm | B13: MDM | C13: API: device list, encryption, OS version, compliance | D13: Weekly | E13: mdm/compliance/<date>.csv | F13: INF-08
A14: col-backups | B14: BKP | C14: API: backup job status, vault lock config | D14: Daily | E14: backup/jobs/<date>.csv | F14: BCP-01
... A22: col-gh-alerts | B22: GitHub, ServiceNow | C22: /orgs/{org}/code-scanning|secret-scanning|dependabot/alerts; join ServiceNow ticket + SLA state | D22: Weekly | E22: vuln/github/<date>.csv | F22: CHG-04, VUL-01, INF-06

Sheet PBC Evidence List
A1: Request ID | B1: Control ID | C1: Control Title | D1: Evidence Requested | E1: Period Coverage | F1: Source System | G1: Collector / Method | H1: Owner (Role) | I1: Status | J1: Due Date | K1: Evidence Link | L1: Auditor Comments
A2: PBC-001 | B2: GOV-01 | C2: Security policies approved and published | D2: Policy set with version history and approval record | E2: Each occurrence in period | F2: GRC | G2: Manual upload | H2: CISO / Security Lead | I2: Not started
A3: PBC-002 | B3: GOV-01 | C3: Security policies approved and published | D3: publication location screenshot | E3: Each occurrence in period | F3: GRC | G3: Manual upload | H3: CISO / Security Lead | I3: Not started
A4: PBC-003 | B4: GOV-02 | C4: Board / oversight committee security review | D4: Board / committee meeting minutes and presentation deck | E4: Each occurrence in period | F4: GRC | G4: Manual upload | H4: CEO | I4: Not started
A5: PBC-004 | B5: GOV-03 | C5: Organization chart and security roles defined | D5: Org chart export | E5: Each occurrence in period | F5: HRIS, GRC | G5: Manual upload | H5: Head of People | I5: Not started
A6: PBC-005 | B6: GOV-03 | C6: Organization chart and security roles defined | D6: RACI document with review date | E6: Each occurrence in period | F6: HRIS, GRC | G6: Manual upload | H6: Head of People | I6: Not started
A7: PBC-006 | B7: GOV-04 | C7: Security and compliance steering meeting | D7: Meeting agendas, minutes and action tracker | E7: Each occurrence in period | F7: ITSM, GRC | G7: Manual upload | H7: CISO / Security Lead | I7: Not started
A8: PBC-007 | B8: GOV-05 | C8: Internal control self-assessment | D8: Quarterly attestations | E8: Each occurrence in period | F8: GRC, ITSM | G8: Manual upload | H8: Compliance Manager | I8: Not started
A9: PBC-008 | B9: GOV-05 | C9: Internal control self-assessment | D9: internal assessment report | E9: Each occurrence in period | F9: GRC, ITSM | G9: Manual upload | H9: Compliance Manager | I9: Not started
A10: PBC-009 | B10: GOV-05 | C10: Internal control self-assessment | D10: deficiency tickets | E10: Each occurrence in period | F10: GRC, ITSM | G10: Manual upload | H10: Compliance Manager | I10: Not started
A11: PBC-010 | B11: GOV-06 | C11: External communication of commitments | D11: MSA/DPA templates | E11: Each occurrence in period | F11: GRC | G11: Manual upload | H11: Legal / Compliance | I11: Not started
A12: PBC-011 | B12: GOV-06 | C12: External communication of commitments | D12: status page history | E12: Each occurrence in period | F12: GRC | G12: Manual upload | H12: Legal / Compliance | I12: Not started
A13: PBC-012 | B13: GOV-06 | C13: External communication of commitments | D13: customer notices | E13: Each occurrence in period | F13: GRC | G13: Manual upload | H13: Legal / Compliance | I13: Not started
... A136: PBC-135 | B136: BCP-04 | C136: Resilient architecture | D136: multi-AZ config export | E136: Point in time + period | F136: CLD, K8S, IAC | G136: Manual upload | H136: Platform Engineering | I136: Not started

Sheet Risk Register
A1: Risk ID | B1: Risk Description | C1: Asset / Subsystem | D1: Threat Source | E1: Likelihood (1-5) | F1: Impact (1-5) | G1: Inherent Score | H1: Inherent Rating | I1: Mitigating Controls | J1: Residual L (1-5) | K1: Residual Score | L1: Residual Rating | M1: Residual I (1-5) | N1: Treatment | O1: Risk Owner | P1: Review Date
A2: R-01 | B2: Unauthorized code merged to production branch | C2: SCM, CI | D2: Insider / compromised dev account | E2: 3 | F2: 5 | G2: =E2*F2 -> 15 | H2: =IF(G2>=15,"High",IF(G2>=8,"Medium","Low")) -> High | I2: CHG-01, CHG-02, IAM-01, MON-03 | J2: 1 | K2: =J2*M2 -> 5 | L2: =IF(K2>=15,"High",IF(K2>=8,"Medium","Low")) -> Low | M2: 5 | N2: Mitigate | O2: Engineering Manager
A3: R-02 | B3: CI/CD pipeline compromise (malicious workflow, poisoned third-party action) | C3: CI | D3: External attacker / supply chain | E3: 3 | F3: 5 | G3: =E3*F3 -> 15 | H3: =IF(G3>=15,"High",IF(G3>=8,"Medium","Low")) -> High | I3: CHG-11, CHG-07, IAM-07, INF-06 | J3: 2 | K3: =J3*M3 -> 8 | L3: =IF(K3>=15,"High",IF(K3>=8,"Medium","Low")) -> Medium | M3: 4 | N3: Mitigate | O3: Platform Engineering
A4: R-03 | B4: Leaked long-lived cloud credentials | C4: CLD, VAULT | D4: External attacker | E4: 3 | F4: 5 | G4: =E4*F4 -> 15 | H4: =IF(G4>=15,"High",IF(G4>=8,"Medium","Low")) -> High | I4: IAM-07, INF-06, MON-03 | J4: 1 | K4: =J4*M4 -> 4 | L4: =IF(K4>=15,"High",IF(K4>=8,"Medium","Low")) -> Low | M4: 4 | N4: Mitigate | O4: Platform Engineering
A5: R-04 | B5: Terminated employee retains access | C5: IDP, all SaaS | D5: Former insider | E5: 3 | F5: 4 | G5: =E5*F5 -> 12 | H5: =IF(G5>=15,"High",IF(G5>=8,"Medium","Low")) -> Medium | I5: IAM-03, IAM-04 | J5: 1 | K5: =J5*M5 -> 4 | L5: =IF(K5>=15,"High",IF(K5>=8,"Medium","Low")) -> Low | M5: 4 | N5: Mitigate | O5: IT / Identity Admin
A6: R-05 | B6: Excessive privileged access in production | C6: CLD, K8S | D6: Insider error / misuse | E6: 3 | F6: 4 | G6: =E6*F6 -> 12 | H6: =IF(G6>=15,"High",IF(G6>=8,"Medium","Low")) -> Medium | I6: IAM-05, IAM-06, IAM-04 | J6: 2 | K6: =J6*M6 -> 6 | L6: =IF(K6>=15,"High",IF(K6>=8,"Medium","Low")) -> Low | M6: 3 | N6: Mitigate | O6: Engineering Manager
A7: R-06 | B7: Cloud misconfiguration exposes customer data publicly | C7: CLD | D7: Human error | E7: 3 | F7: 5 | G7: =E7*F7 -> 15 | H7: =IF(G7>=15,"High",IF(G7>=8,"Medium","Low")) -> High | I7: INF-02, INF-11, CHG-10 | J7: 1 | K7: =J7*M7 -> 5 | L7: =IF(K7>=15,"High",IF(K7>=8,"Medium","Low")) -> Low | M7: 5 | N7: Mitigate | O7: Platform Engineering
A8: R-07 | B8: Unpatched critical vulnerability exploited | C8: CLD, K8S, REG | D8: External attacker | E8: 3 | F8: 5 | G8: =E8*F8 -> 15 | H8: =IF(G8>=15,"High",IF(G8>=8,"Medium","Low")) -> High | I8: VUL-01, VUL-03, CHG-04 | J8: 2 | K8: =J8*M8 -> 8 | L8: =IF(K8>=15,"High",IF(K8>=8,"Medium","Low")) -> Medium | M8: 4 | N8: Mitigate | O8: AppSec Lead
A9: R-08 | B9: Security event not detected due to logging gap | C9: SIEM | D9: Any | E9: 3 | F9: 4 | G9: =E9*F9 -> 12 | H9: =IF(G9>=15,"High",IF(G9>=8,"Medium","Low")) -> Medium | I9: MON-01, MON-02, MON-06 | J9: 1 | K9: =J9*M9 -> 4 | L9: =IF(K9>=15,"High",IF(K9>=8,"Medium","Low")) -> Low | M9: 4 | N9: Mitigate | O9: Security Operations
A10: R-09 | B10: Ransomware / destructive attack destroys production data | C10: CLD, BKP | D10: External attacker | E10: 2 | F10: 5 | G10: =E10*F10 -> 10 | H10: =IF(G10>=15,"High",IF(G10>=8,"Medium","Low")) -> Medium | I10: BCP-01, BCP-02, IAM-05 | J10: 1 | K10: =J10*M10 -> 4 | L10: =IF(K10>=15,"High",IF(K10>=8,"Medium","Low")) -> Low | M10: 4 | N10: Mitigate | O10: SRE Lead
A11: R-10 | B11: Regional cloud outage causes extended downtime | C11: CLD | D11: Environmental / provider | E11: 2 | F11: 4 | G11: =E11*F11 -> 8 | H11: =IF(G11>=15,"High",IF(G11>=8,"Medium","Low")) -> Medium | I11: BCP-03, BCP-04 | J11: 2 | K11: =J11*M11 -> 6 | L11: =IF(K11>=15,"High",IF(K11>=8,"Medium","Low")) -> Low | M11: 3 | N11: Mitigate / Accept residual | O11: SRE Lead
A12: R-11 | B12: Critical vendor breach impacts customer data | C12: Vendors | D12: Third party | E12: 2 | F12: 4 | G12: =E12*F12 -> 8 | H12: =IF(G12>=15,"High",IF(G12>=8,"Medium","Low")) -> Medium | I12: VEN-01, VEN-02, VEN-03 | J12: 2 | K12: =J12*M12 -> 6 | L12: =IF(K12>=15,"High",IF(K12>=8,"Medium","Low")) -> Low | M12: 3 | N12: Mitigate / Transfer | O12: Compliance Manager
A13: R-12 | B13: Phishing leads to account takeover | C13: IDP, MDM | D13: External attacker | E13: 4 | F13: 4 | G13: =E13*F13 -> 16 | H13: =IF(G13>=15,"High",IF(G13>=8,"Medium","Low")) -> High | I13: IAM-01, HR-03, INF-08 | J13: 1 | K13: =J13*M13 -> 4 | L13: =IF(K13>=15,"High",IF(K13>=8,"Medium","Low")) -> Low | M13: 4 | N13: Mitigate | O13: IT / Identity Admin
... A19: R-18 | B19: Incident mishandled / late customer notification | C19: ITSM, ONC | D19: Process failure | E19: 2 | F19: 4 | G19: =E19*F19 -> 8 | H19: =IF(G19>=15,"High",IF(G19>=8,"Medium","Low")) -> Medium | I19: IR-01, IR-02, IR-04 | J19: 1 | K19: =J19*M19 -> 3 | L19: =IF(K19>=15,"High",IF(K19>=8,"Medium","Low")) -> Low | M19: 3 | N19: Mitigate | O19: CISO / Security Lead
A21: Scoring: Likelihood × Impact on 1–5 scales. High ≥ 15, Medium 8–14, Low ≤ 7. Blue values are seed assumptions – re-score for your environment during the annual risk assessment (RSK-01).

Sheet Compliance Calendar
A1: Activity | B1: Control | C1: M1 | D1: M2 | E1: M3 | F1: M4 | G1: M5 | H1: M6 | I1: M7 | J1: M8 | K1: M9 | L1: M10 | M1: M11 | N1: M12 | O1: Occurrences
A2: Policy review & approval | B2: GOV-01 | C2: ● | O2: =COUNTIF(C2:N2,"●") -> 1
A3: Board / oversight security update | B3: GOV-02 | M3: ● | O3: =COUNTIF(C3:N3,"●") -> 1
A4: Security steering meeting | B4: GOV-04 | C4: ● | F4: ● | I4: ● | L4: ● | O4: =COUNTIF(C4:N4,"●") -> 4
A5: Control owner attestations | B5: GOV-05 | E5: ● | H5: ● | K5: ● | N5: ● | O5: =COUNTIF(C5:N5,"●") -> 4
A6: Risk assessment | B6: RSK-01 | D6: ● | O6: =COUNTIF(C6:N6,"●") -> 1
A7: User access review (all in-scope systems) | B7: IAM-04 | C7: ● | F7: ● | I7: ● | L7: ● | O7: =COUNTIF(C7:N7,"●") -> 4
A8: Vendor reviews (critical) | B8: VEN-02 | G8: ● | O8: =COUNTIF(C8:N8,"●") -> 1
A9: Security awareness training campaign | B9: HR-03 | E9: ● | O9: =COUNTIF(C9:N9,"●") -> 1
A10: Penetration test | B10: VUL-02 | H10: ● | O10: =COUNTIF(C10:N10,"●") -> 1
A11: Backup restore test | B11: BCP-02 | D11: ● | G11: ● | J11: ● | M11: ● | O11: =COUNTIF(C11:N11,"●") -> 4
A12: DR test | B12: BCP-03 | K12: ● | O12: =COUNTIF(C12:N12,"●") -> 1
A13: IR tabletop exercise | B13: IR-04 | J13: ● | O13: =COUNTIF(C13:N13,"●") -> 1
A14: Asset inventory review | B14: INF-07 | E14: ● | H14: ● | K14: ● | N14: ● | O14: =COUNTIF(C14:N14,"●") -> 4
A15: Non-pipeline production change query | B15: CHG-05 | C15: ● | D15: ● | E15: ● | F15: ● | G15: ● | H15: ● | I15: ● | J15: ● | K15: ● | L15: ● | M15: ● | N15: ● | O15: =COUNTIF(C15:N15,"●") -> 12
A16: Patch / base image rebuild | B16: VUL-03 | C16: ● | D16: ● | E16: ● | F16: ● | G16: ● | H16: ● | I16: ● | J16: ● | K16: ● | L16: ● | M16: ● | N16: ● | O16: =COUNTIF(C16:N16,"●") -> 12
A17: System description review | B17: GOV-08 | N17: ● | O17: =COUNTIF(C17:N17,"●") -> 1
A18: Evidence package QA (sample pull) | B18: GOV-05 | E18: ● | H18: ● | K18: ● | N18: ● | O18: =COUNTIF(C18:N18,"●") -> 4
A20: M1 = first month of the observation period. Shift activities to suit your calendar; keep quarterly activities evenly spaced so every quarter is represented in the period.

Sheet Sampling Guide
A1: Sampling Basis | B1: Typical Minimum Sample | C1: Typical Range | D1: Notes
A2: Annual | B2: 1 | C2: 1 | D2: Source: common practice aligned with AICPA Audit Sampling guidance; your audit firm's methodology governs.
A3: Quarterly | B3: 2 | C3: 2
A4: Monthly | B4: 2 | C4: 2–3
A5: Weekly | B5: 5 | C5: 5–10
A6: Daily | B6: 20 | C6: 20–40
A7: Per event / multiple times per day | B7: 25 | C7: 25–60 (depends on population size)
A8: Automated (continuous) | B8: 1 | C8: 1 per configuration, plus ITGC reliance and change testing | D8: Automated controls: test of one plus reliance on ITGCs (change mgmt & access over the config). Show config was unchanged across the period via drift/change logs.
